<?xml version="1.0" encoding="utf-8"?>
<cBlueprintLoader xmlns:d="http://www.kuju.com/TnT/2003/Delta" d:version="1.0">
	<Blueprint>
		<cInputMapperBlueprint xmlns:d="http://www.kuju.com/TnT/2003/Delta" d:version="1.0">
			<RemapperName d:type="cDeltaString">460_expert</RemapperName>
			<Map>
				<iInputMapper-cInputMapEntry d:id="51961">
					<State d:type="sInt32">0</State>
					<Device d:type="cDeltaString">Keyboard</Device>
					<ButtonState d:type="cDeltaString">ButtonDown</ButtonState>
					<Button d:type="cDeltaString">Key_P</Button>
					<ShiftButton d:type="cDeltaString">NoShift</ShiftButton>
					<Axis d:type="cDeltaString">NoAxis</Axis>
					<Name d:type="cDeltaString">ToggleControl</Name>
					<Parameter d:type="cDeltaString">VirtualPantographControl</Parameter>
					<NewState d:type="sInt32">0</NewState>
				</iInputMapper-cInputMapEntry>
				<iInputMapper-cInputMapEntry d:id="51971">
					<State d:type="sInt32">0</State>
					<Device d:type="cDeltaString">Keyboard</Device>
					<ButtonState d:type="cDeltaString">ButtonDown</ButtonState>
					<Button d:type="cDeltaString">Key_D</Button>
					<ShiftButton d:type="cDeltaString">NoShift</ShiftButton>
					<Axis d:type="cDeltaString">NoAxis</Axis>
					<Name d:type="cDeltaString">DecreaseControlStart</Name>
					<Parameter d:type="cDeltaString">RadicNouzovy</Parameter>
					<NewState d:type="sInt32">0</NewState>
				</iInputMapper-cInputMapEntry>
				<iInputMapper-cInputMapEntry d:id="51981">
					<State d:type="sInt32">0</State>
					<Device d:type="cDeltaString">Keyboard</Device>
					<ButtonState d:type="cDeltaString">ButtonDown</ButtonState>
					<Button d:type="cDeltaString">Key_D</Button>
					<ShiftButton d:type="cDeltaString">NoShift</ShiftButton>
					<Axis d:type="cDeltaString">NoAxis</Axis>
					<Name d:type="cDeltaString">DecreaseControlStart</Name>
					<Parameter d:type="cDeltaString">VirtualThrottleAndBrake</Parameter>
					<NewState d:type="sInt32">0</NewState>
				</iInputMapper-cInputMapEntry>
				<iInputMapper-cInputMapEntry d:id="51991">
					<State d:type="sInt32">0</State>
					<Device d:type="cDeltaString">Keyboard</Device>
					<ButtonState d:type="cDeltaString">ButtonUp</ButtonState>
					<Button d:type="cDeltaString">Key_D</Button>
					<ShiftButton d:type="cDeltaString">NoShift</ShiftButton>
					<Axis d:type="cDeltaString">NoAxis</Axis>
					<Name d:type="cDeltaString">DecreaseControlStop</Name>
					<Parameter d:type="cDeltaString">RadicNouzovy</Parameter>
					<NewState d:type="sInt32">0</NewState>
				</iInputMapper-cInputMapEntry>
				<iInputMapper-cInputMapEntry d:id="52001">
					<State d:type="sInt32">0</State>
					<Device d:type="cDeltaString">Keyboard</Device>
					<ButtonState d:type="cDeltaString">ButtonUp</ButtonState>
					<Button d:type="cDeltaString">Key_D</Button>
					<ShiftButton d:type="cDeltaString">NoShift</ShiftButton>
					<Axis d:type="cDeltaString">NoAxis</Axis>
					<Name d:type="cDeltaString">DecreaseControlStop</Name>
					<Parameter d:type="cDeltaString">VirtualThrottleAndBrake</Parameter>
					<NewState d:type="sInt32">0</NewState>
				</iInputMapper-cInputMapEntry>
				<iInputMapper-cInputMapEntry d:id="52011">
					<State d:type="sInt32">0</State>
					<Device d:type="cDeltaString">Keyboard</Device>
					<ButtonState d:type="cDeltaString">ButtonDown</ButtonState>
					<Button d:type="cDeltaString">Key_A</Button>
					<ShiftButton d:type="cDeltaString">NoShift</ShiftButton>
					<Axis d:type="cDeltaString">NoAxis</Axis>
					<Name d:type="cDeltaString">IncreaseControlStart</Name>
					<Parameter d:type="cDeltaString">RadicNouzovy</Parameter>
					<NewState d:type="sInt32">0</NewState>
				</iInputMapper-cInputMapEntry>
				<iInputMapper-cInputMapEntry d:id="52021">
					<State d:type="sInt32">0</State>
					<Device d:type="cDeltaString">Keyboard</Device>
					<ButtonState d:type="cDeltaString">ButtonDown</ButtonState>
					<Button d:type="cDeltaString">Key_A</Button>
					<ShiftButton d:type="cDeltaString">NoShift</ShiftButton>
					<Axis d:type="cDeltaString">NoAxis</Axis>
					<Name d:type="cDeltaString">IncreaseControlStart</Name>
					<Parameter d:type="cDeltaString">VirtualThrottleAndBrake</Parameter>
					<NewState d:type="sInt32">0</NewState>
				</iInputMapper-cInputMapEntry>
				<iInputMapper-cInputMapEntry d:id="52031">
					<State d:type="sInt32">0</State>
					<Device d:type="cDeltaString">Keyboard</Device>
					<ButtonState d:type="cDeltaString">ButtonUp</ButtonState>
					<Button d:type="cDeltaString">Key_A</Button>
					<ShiftButton d:type="cDeltaString">NoShift</ShiftButton>
					<Axis d:type="cDeltaString">NoAxis</Axis>
					<Name d:type="cDeltaString">IncreaseControlStop</Name>
					<Parameter d:type="cDeltaString">RadicNouzovy</Parameter>
					<NewState d:type="sInt32">0</NewState>
				</iInputMapper-cInputMapEntry>
				<iInputMapper-cInputMapEntry d:id="52041">
					<State d:type="sInt32">0</State>
					<Device d:type="cDeltaString">Keyboard</Device>
					<ButtonState d:type="cDeltaString">ButtonUp</ButtonState>
					<Button d:type="cDeltaString">Key_A</Button>
					<ShiftButton d:type="cDeltaString">NoShift</ShiftButton>
					<Axis d:type="cDeltaString">NoAxis</Axis>
					<Name d:type="cDeltaString">IncreaseControlStop</Name>
					<Parameter d:type="cDeltaString">VirtualThrottleAndBrake</Parameter>
					<NewState d:type="sInt32">0</NewState>
				</iInputMapper-cInputMapEntry>
				<iInputMapper-cInputMapEntry d:id="52051">
					<State d:type="sInt32">0</State>
					<Device d:type="cDeltaString">Keyboard</Device>
					<ButtonState d:type="cDeltaString">ButtonDown</ButtonState>
					<Button d:type="cDeltaString">Key_W</Button>
					<ShiftButton d:type="cDeltaString">NoShift</ShiftButton>
					<Axis d:type="cDeltaString">NoAxis</Axis>
					<Name d:type="cDeltaString">IncreaseControlStart</Name>
					<Parameter d:type="cDeltaString">UserVirtualReverser</Parameter>
					<NewState d:type="sInt32">0</NewState>
				</iInputMapper-cInputMapEntry>
				<iInputMapper-cInputMapEntry d:id="52061">
					<State d:type="sInt32">0</State>
					<Device d:type="cDeltaString">Keyboard</Device>
					<ButtonState d:type="cDeltaString">ButtonUp</ButtonState>
					<Button d:type="cDeltaString">Key_W</Button>
					<ShiftButton d:type="cDeltaString">NoShift</ShiftButton>
					<Axis d:type="cDeltaString">NoAxis</Axis>
					<Name d:type="cDeltaString">IncreaseControlStop</Name>
					<Parameter d:type="cDeltaString">UserVirtualReverser</Parameter>
					<NewState d:type="sInt32">0</NewState>
				</iInputMapper-cInputMapEntry>
				<iInputMapper-cInputMapEntry d:id="52071">
					<State d:type="sInt32">0</State>
					<Device d:type="cDeltaString">Keyboard</Device>
					<ButtonState d:type="cDeltaString">ButtonDown</ButtonState>
					<Button d:type="cDeltaString">Key_S</Button>
					<ShiftButton d:type="cDeltaString">NoShift</ShiftButton>
					<Axis d:type="cDeltaString">NoAxis</Axis>
					<Name d:type="cDeltaString">DecreaseControlStart</Name>
					<Parameter d:type="cDeltaString">UserVirtualReverser</Parameter>
					<NewState d:type="sInt32">0</NewState>
				</iInputMapper-cInputMapEntry>
				<iInputMapper-cInputMapEntry d:id="52081">
					<State d:type="sInt32">0</State>
					<Device d:type="cDeltaString">Keyboard</Device>
					<ButtonState d:type="cDeltaString">ButtonUp</ButtonState>
					<Button d:type="cDeltaString">Key_S</Button>
					<ShiftButton d:type="cDeltaString">NoShift</ShiftButton>
					<Axis d:type="cDeltaString">NoAxis</Axis>
					<Name d:type="cDeltaString">DecreaseControlStop</Name>
					<Parameter d:type="cDeltaString">UserVirtualReverser</Parameter>
					<NewState d:type="sInt32">0</NewState>
				</iInputMapper-cInputMapEntry>
				<iInputMapper-cInputMapEntry d:id="52091">
					<State d:type="sInt32">0</State>
					<Device d:type="cDeltaString">Keyboard</Device>
					<ButtonState d:type="cDeltaString">ButtonDown</ButtonState>
					<Button d:type="cDeltaString">Key_Left_Bracket</Button>
					<ShiftButton d:type="cDeltaString">NoShift</ShiftButton>
					<Axis d:type="cDeltaString">NoAxis</Axis>
					<Name d:type="cDeltaString">DecreaseControlStart</Name>
					<Parameter d:type="cDeltaString">EngineBrakeControl</Parameter>
					<NewState d:type="sInt32">0</NewState>
				</iInputMapper-cInputMapEntry>
				<iInputMapper-cInputMapEntry d:id="52101">
					<State d:type="sInt32">0</State>
					<Device d:type="cDeltaString">Keyboard</Device>
					<ButtonState d:type="cDeltaString">ButtonUp</ButtonState>
					<Button d:type="cDeltaString">Key_Left_Bracket</Button>
					<ShiftButton d:type="cDeltaString">NoShift</ShiftButton>
					<Axis d:type="cDeltaString">NoAxis</Axis>
					<Name d:type="cDeltaString">DecreaseControlStop</Name>
					<Parameter d:type="cDeltaString">EngineBrakeControl</Parameter>
					<NewState d:type="sInt32">0</NewState>
				</iInputMapper-cInputMapEntry>
				<iInputMapper-cInputMapEntry d:id="52111">
					<State d:type="sInt32">0</State>
					<Device d:type="cDeltaString">Keyboard</Device>
					<ButtonState d:type="cDeltaString">ButtonDown</ButtonState>
					<Button d:type="cDeltaString">Key_Right_Bracket</Button>
					<ShiftButton d:type="cDeltaString">NoShift</ShiftButton>
					<Axis d:type="cDeltaString">NoAxis</Axis>
					<Name d:type="cDeltaString">IncreaseControlStart</Name>
					<Parameter d:type="cDeltaString">EngineBrakeControl</Parameter>
					<NewState d:type="sInt32">0</NewState>
				</iInputMapper-cInputMapEntry>
				<iInputMapper-cInputMapEntry d:id="52121">
					<State d:type="sInt32">0</State>
					<Device d:type="cDeltaString">Keyboard</Device>
					<ButtonState d:type="cDeltaString">ButtonUp</ButtonState>
					<Button d:type="cDeltaString">Key_Right_Bracket</Button>
					<ShiftButton d:type="cDeltaString">NoShift</ShiftButton>
					<Axis d:type="cDeltaString">NoAxis</Axis>
					<Name d:type="cDeltaString">IncreaseControlStop</Name>
					<Parameter d:type="cDeltaString">EngineBrakeControl</Parameter>
					<NewState d:type="sInt32">0</NewState>
				</iInputMapper-cInputMapEntry>
				<iInputMapper-cInputMapEntry d:id="52131">
					<State d:type="sInt32">0</State>
					<Device d:type="cDeltaString">Keyboard</Device>
					<ButtonState d:type="cDeltaString">ButtonDown</ButtonState>
					<Button d:type="cDeltaString">Key_SemiColon</Button>
					<ShiftButton d:type="cDeltaString">NoShift</ShiftButton>
					<Axis d:type="cDeltaString">NoAxis</Axis>
					<Name d:type="cDeltaString">DecreaseControlStart</Name>
					<Parameter d:type="cDeltaString">VirtualBrake</Parameter>
					<NewState d:type="sInt32">0</NewState>
				</iInputMapper-cInputMapEntry>
				<iInputMapper-cInputMapEntry d:id="52141">
					<State d:type="sInt32">0</State>
					<Device d:type="cDeltaString">Keyboard</Device>
					<ButtonState d:type="cDeltaString">ButtonUp</ButtonState>
					<Button d:type="cDeltaString">Key_SemiColon</Button>
					<ShiftButton d:type="cDeltaString">NoShift</ShiftButton>
					<Axis d:type="cDeltaString">NoAxis</Axis>
					<Name d:type="cDeltaString">DecreaseControlStop</Name>
					<Parameter d:type="cDeltaString">VirtualBrake</Parameter>
					<NewState d:type="sInt32">0</NewState>
				</iInputMapper-cInputMapEntry>
				<iInputMapper-cInputMapEntry d:id="52151">
					<State d:type="sInt32">0</State>
					<Device d:type="cDeltaString">Keyboard</Device>
					<ButtonState d:type="cDeltaString">ButtonDown</ButtonState>
					<Button d:type="cDeltaString">Key_Apostophe</Button>
					<ShiftButton d:type="cDeltaString">NoShift</ShiftButton>
					<Axis d:type="cDeltaString">NoAxis</Axis>
					<Name d:type="cDeltaString">IncreaseControlStart</Name>
					<Parameter d:type="cDeltaString">VirtualBrake</Parameter>
					<NewState d:type="sInt32">0</NewState>
				</iInputMapper-cInputMapEntry>
				<iInputMapper-cInputMapEntry d:id="52161">
					<State d:type="sInt32">0</State>
					<Device d:type="cDeltaString">Keyboard</Device>
					<ButtonState d:type="cDeltaString">ButtonUp</ButtonState>
					<Button d:type="cDeltaString">Key_Apostophe</Button>
					<ShiftButton d:type="cDeltaString">NoShift</ShiftButton>
					<Axis d:type="cDeltaString">NoAxis</Axis>
					<Name d:type="cDeltaString">IncreaseControlStop</Name>
					<Parameter d:type="cDeltaString">VirtualBrake</Parameter>
					<NewState d:type="sInt32">0</NewState>
				</iInputMapper-cInputMapEntry>
				<iInputMapper-cInputMapEntry d:id="52171">
					<State d:type="sInt32">0</State>
					<Device d:type="cDeltaString">Keyboard</Device>
					<ButtonState d:type="cDeltaString">ButtonDown</ButtonState>
					<Button d:type="cDeltaString">Key_H</Button>
					<ShiftButton d:type="cDeltaString">NoShift</ShiftButton>
					<Axis d:type="cDeltaString">NoAxis</Axis>
					<Name d:type="cDeltaString">IncreaseControlStart</Name>
					<Parameter d:type="cDeltaString">Headlights</Parameter>
					<NewState d:type="sInt32">0</NewState>
				</iInputMapper-cInputMapEntry>
				<iInputMapper-cInputMapEntry d:id="52181">
					<State d:type="sInt32">0</State>
					<Device d:type="cDeltaString">Keyboard</Device>
					<ButtonState d:type="cDeltaString">ButtonUp</ButtonState>
					<Button d:type="cDeltaString">Key_H</Button>
					<ShiftButton d:type="cDeltaString">NoShift</ShiftButton>
					<Axis d:type="cDeltaString">NoAxis</Axis>
					<Name d:type="cDeltaString">IncreaseControlStop</Name>
					<Parameter d:type="cDeltaString">Headlights</Parameter>
					<NewState d:type="sInt32">0</NewState>
				</iInputMapper-cInputMapEntry>
				<iInputMapper-cInputMapEntry d:id="52191">
					<State d:type="sInt32">0</State>
					<Device d:type="cDeltaString">Keyboard</Device>
					<ButtonState d:type="cDeltaString">ButtonDown</ButtonState>
					<Button d:type="cDeltaString">Key_H</Button>
					<ShiftButton d:type="cDeltaString">Shift</ShiftButton>
					<Axis d:type="cDeltaString">NoAxis</Axis>
					<Name d:type="cDeltaString">DecreaseControlStart</Name>
					<Parameter d:type="cDeltaString">Headlights</Parameter>
					<NewState d:type="sInt32">0</NewState>
				</iInputMapper-cInputMapEntry>
				<iInputMapper-cInputMapEntry d:id="52201">
					<State d:type="sInt32">0</State>
					<Device d:type="cDeltaString">Keyboard</Device>
					<ButtonState d:type="cDeltaString">ButtonUp</ButtonState>
					<Button d:type="cDeltaString">Key_H</Button>
					<ShiftButton d:type="cDeltaString">Shift</ShiftButton>
					<Axis d:type="cDeltaString">NoAxis</Axis>
					<Name d:type="cDeltaString">DecreaseControlStop</Name>
					<Parameter d:type="cDeltaString">Headlights</Parameter>
					<NewState d:type="sInt32">0</NewState>
				</iInputMapper-cInputMapEntry>
				<iInputMapper-cInputMapEntry d:id="52211">
					<State d:type="sInt32">0</State>
					<Device d:type="cDeltaString">Keyboard</Device>
					<ButtonState d:type="cDeltaString">ButtonDown</ButtonState>
					<Button d:type="cDeltaString">Key_X</Button>
					<ShiftButton d:type="cDeltaString">NoShift</ShiftButton>
					<Axis d:type="cDeltaString">NoAxis</Axis>
					<Name d:type="cDeltaString">IncreaseControlStart</Name>
					<Parameter d:type="cDeltaString">Sander</Parameter>
					<NewState d:type="sInt32">0</NewState>
				</iInputMapper-cInputMapEntry>
				<iInputMapper-cInputMapEntry d:id="52221">
					<State d:type="sInt32">0</State>
					<Device d:type="cDeltaString">Keyboard</Device>
					<ButtonState d:type="cDeltaString">ButtonUp</ButtonState>
					<Button d:type="cDeltaString">Key_X</Button>
					<ShiftButton d:type="cDeltaString">NoShift</ShiftButton>
					<Axis d:type="cDeltaString">NoAxis</Axis>
					<Name d:type="cDeltaString">DecreaseControlStart</Name>
					<Parameter d:type="cDeltaString">Sander</Parameter>
					<NewState d:type="sInt32">0</NewState>
				</iInputMapper-cInputMapEntry>
				<iInputMapper-cInputMapEntry d:id="52231">
					<State d:type="sInt32">0</State>
					<Device d:type="cDeltaString">Keyboard</Device>
					<ButtonState d:type="cDeltaString">ButtonDown</ButtonState>
					<Button d:type="cDeltaString">Key_V</Button>
					<ShiftButton d:type="cDeltaString">NoShift</ShiftButton>
					<Axis d:type="cDeltaString">NoAxis</Axis>
					<Name d:type="cDeltaString">ToggleControl</Name>
					<Parameter d:type="cDeltaString">Wipers</Parameter>
					<NewState d:type="sInt32">0</NewState>
				</iInputMapper-cInputMapEntry>
				<iInputMapper-cInputMapEntry d:id="52241">
					<State d:type="sInt32">0</State>
					<Device d:type="cDeltaString">Keyboard</Device>
					<ButtonState d:type="cDeltaString">ButtonDown</ButtonState>
					<Button d:type="cDeltaString">Key_B</Button>
					<ShiftButton d:type="cDeltaString">NoShift</ShiftButton>
					<Axis d:type="cDeltaString">NoAxis</Axis>
					<Name d:type="cDeltaString">IncreaseControlStart</Name>
					<Parameter d:type="cDeltaString">Horn</Parameter>
					<NewState d:type="sInt32">0</NewState>
				</iInputMapper-cInputMapEntry>
				<iInputMapper-cInputMapEntry d:id="52251">
					<State d:type="sInt32">0</State>
					<Device d:type="cDeltaString">Keyboard</Device>
					<ButtonState d:type="cDeltaString">ButtonUp</ButtonState>
					<Button d:type="cDeltaString">Key_B</Button>
					<ShiftButton d:type="cDeltaString">NoShift</ShiftButton>
					<Axis d:type="cDeltaString">NoAxis</Axis>
					<Name d:type="cDeltaString">DecreaseControlStart</Name>
					<Parameter d:type="cDeltaString">Horn</Parameter>
					<NewState d:type="sInt32">0</NewState>
				</iInputMapper-cInputMapEntry>
				<iInputMapper-cInputMapEntry d:id="52261">
					<State d:type="sInt32">0</State>
					<Device d:type="cDeltaString">Keyboard</Device>
					<ButtonState d:type="cDeltaString">ButtonDown</ButtonState>
					<Button d:type="cDeltaString">Key_N</Button>
					<ShiftButton d:type="cDeltaString">NoShift</ShiftButton>
					<Axis d:type="cDeltaString">NoAxis</Axis>
					<Name d:type="cDeltaString">IncreaseControlStart</Name>
					<Parameter d:type="cDeltaString">Bell</Parameter>
					<NewState d:type="sInt32">0</NewState>
				</iInputMapper-cInputMapEntry>
				<iInputMapper-cInputMapEntry d:id="52271">
					<State d:type="sInt32">0</State>
					<Device d:type="cDeltaString">Keyboard</Device>
					<ButtonState d:type="cDeltaString">ButtonUp</ButtonState>
					<Button d:type="cDeltaString">Key_N</Button>
					<ShiftButton d:type="cDeltaString">NoShift</ShiftButton>
					<Axis d:type="cDeltaString">NoAxis</Axis>
					<Name d:type="cDeltaString">DecreaseControlStart</Name>
					<Parameter d:type="cDeltaString">Bell</Parameter>
					<NewState d:type="sInt32">0</NewState>
				</iInputMapper-cInputMapEntry>
				<iInputMapper-cInputMapEntry d:id="52281">
					<State d:type="sInt32">0</State>
					<Device d:type="cDeltaString">Keyboard</Device>
					<ButtonState d:type="cDeltaString">ButtonDown</ButtonState>
					<Button d:type="cDeltaString">Key_M</Button>
					<ShiftButton d:type="cDeltaString">NoShift</ShiftButton>
					<Axis d:type="cDeltaString">NoAxis</Axis>
					<Name d:type="cDeltaString">IncreaseControlStart</Name>
					<Parameter d:type="cDeltaString">VolbaPozicKonecCelo</Parameter>
					<NewState d:type="sInt32">0</NewState>
				</iInputMapper-cInputMapEntry>
				<iInputMapper-cInputMapEntry d:id="52291">
					<State d:type="sInt32">0</State>
					<Device d:type="cDeltaString">Keyboard</Device>
					<ButtonState d:type="cDeltaString">ButtonUp</ButtonState>
					<Button d:type="cDeltaString">Key_M</Button>
					<ShiftButton d:type="cDeltaString">NoShift</ShiftButton>
					<Axis d:type="cDeltaString">NoAxis</Axis>
					<Name d:type="cDeltaString">IncreaseControlStop</Name>
					<Parameter d:type="cDeltaString">VolbaPozicKonecCelo</Parameter>
					<NewState d:type="sInt32">0</NewState>
				</iInputMapper-cInputMapEntry>
				<iInputMapper-cInputMapEntry d:id="52301">
					<State d:type="sInt32">0</State>
					<Device d:type="cDeltaString">Keyboard</Device>
					<ButtonState d:type="cDeltaString">ButtonDown</ButtonState>
					<Button d:type="cDeltaString">Key_M</Button>
					<ShiftButton d:type="cDeltaString">Shift</ShiftButton>
					<Axis d:type="cDeltaString">NoAxis</Axis>
					<Name d:type="cDeltaString">DecreaseControlStart</Name>
					<Parameter d:type="cDeltaString">VolbaPozicKonecCelo</Parameter>
					<NewState d:type="sInt32">0</NewState>
				</iInputMapper-cInputMapEntry>
				<iInputMapper-cInputMapEntry d:id="52311">
					<State d:type="sInt32">0</State>
					<Device d:type="cDeltaString">Keyboard</Device>
					<ButtonState d:type="cDeltaString">ButtonUp</ButtonState>
					<Button d:type="cDeltaString">Key_M</Button>
					<ShiftButton d:type="cDeltaString">Shift</ShiftButton>
					<Axis d:type="cDeltaString">NoAxis</Axis>
					<Name d:type="cDeltaString">DecreaseControlStop</Name>
					<Parameter d:type="cDeltaString">VolbaPozicKonecCelo</Parameter>
					<NewState d:type="sInt32">0</NewState>
				</iInputMapper-cInputMapEntry>
				<iInputMapper-cInputMapEntry d:id="52321">
					<State d:type="sInt32">0</State>
					<Device d:type="cDeltaString">Keyboard</Device>
					<ButtonState d:type="cDeltaString">ButtonDown</ButtonState>
					<Button d:type="cDeltaString">Key_J</Button>
					<ShiftButton d:type="cDeltaString">NoShift</ShiftButton>
					<Axis d:type="cDeltaString">NoAxis</Axis>
					<Name d:type="cDeltaString">IncreaseControlStart</Name>
					<Parameter d:type="cDeltaString">LevaPoz</Parameter>
					<NewState d:type="sInt32">0</NewState>
				</iInputMapper-cInputMapEntry>
				<iInputMapper-cInputMapEntry d:id="52331">
					<State d:type="sInt32">0</State>
					<Device d:type="cDeltaString">Keyboard</Device>
					<ButtonState d:type="cDeltaString">ButtonUp</ButtonState>
					<Button d:type="cDeltaString">Key_J</Button>
					<ShiftButton d:type="cDeltaString">NoShift</ShiftButton>
					<Axis d:type="cDeltaString">NoAxis</Axis>
					<Name d:type="cDeltaString">IncreaseControlStop</Name>
					<Parameter d:type="cDeltaString">LevaPoz</Parameter>
					<NewState d:type="sInt32">0</NewState>
				</iInputMapper-cInputMapEntry>
				<iInputMapper-cInputMapEntry d:id="52341">
					<State d:type="sInt32">0</State>
					<Device d:type="cDeltaString">Keyboard</Device>
					<ButtonState d:type="cDeltaString">ButtonDown</ButtonState>
					<Button d:type="cDeltaString">Key_J</Button>
					<ShiftButton d:type="cDeltaString">Shift</ShiftButton>
					<Axis d:type="cDeltaString">NoAxis</Axis>
					<Name d:type="cDeltaString">DecreaseControlStart</Name>
					<Parameter d:type="cDeltaString">LevaPoz</Parameter>
					<NewState d:type="sInt32">0</NewState>
				</iInputMapper-cInputMapEntry>
				<iInputMapper-cInputMapEntry d:id="52351">
					<State d:type="sInt32">0</State>
					<Device d:type="cDeltaString">Keyboard</Device>
					<ButtonState d:type="cDeltaString">ButtonUp</ButtonState>
					<Button d:type="cDeltaString">Key_J</Button>
					<ShiftButton d:type="cDeltaString">Shift</ShiftButton>
					<Axis d:type="cDeltaString">NoAxis</Axis>
					<Name d:type="cDeltaString">DecreaseControlStop</Name>
					<Parameter d:type="cDeltaString">LevaPoz</Parameter>
					<NewState d:type="sInt32">0</NewState>
				</iInputMapper-cInputMapEntry>
				<iInputMapper-cInputMapEntry d:id="52361">
					<State d:type="sInt32">0</State>
					<Device d:type="cDeltaString">Keyboard</Device>
					<ButtonState d:type="cDeltaString">ButtonDown</ButtonState>
					<Button d:type="cDeltaString">Key_K</Button>
					<ShiftButton d:type="cDeltaString">NoShift</ShiftButton>
					<Axis d:type="cDeltaString">NoAxis</Axis>
					<Name d:type="cDeltaString">IncreaseControlStart</Name>
					<Parameter d:type="cDeltaString">PravaPoz</Parameter>
					<NewState d:type="sInt32">0</NewState>
				</iInputMapper-cInputMapEntry>
				<iInputMapper-cInputMapEntry d:id="52371">
					<State d:type="sInt32">0</State>
					<Device d:type="cDeltaString">Keyboard</Device>
					<ButtonState d:type="cDeltaString">ButtonUp</ButtonState>
					<Button d:type="cDeltaString">Key_K</Button>
					<ShiftButton d:type="cDeltaString">NoShift</ShiftButton>
					<Axis d:type="cDeltaString">NoAxis</Axis>
					<Name d:type="cDeltaString">IncreaseControlStop</Name>
					<Parameter d:type="cDeltaString">PravaPoz</Parameter>
					<NewState d:type="sInt32">0</NewState>
				</iInputMapper-cInputMapEntry>
				<iInputMapper-cInputMapEntry d:id="52381">
					<State d:type="sInt32">0</State>
					<Device d:type="cDeltaString">Keyboard</Device>
					<ButtonState d:type="cDeltaString">ButtonDown</ButtonState>
					<Button d:type="cDeltaString">Key_K</Button>
					<ShiftButton d:type="cDeltaString">Shift</ShiftButton>
					<Axis d:type="cDeltaString">NoAxis</Axis>
					<Name d:type="cDeltaString">DecreaseControlStart</Name>
					<Parameter d:type="cDeltaString">PravaPoz</Parameter>
					<NewState d:type="sInt32">0</NewState>
				</iInputMapper-cInputMapEntry>
				<iInputMapper-cInputMapEntry d:id="52391">
					<State d:type="sInt32">0</State>
					<Device d:type="cDeltaString">Keyboard</Device>
					<ButtonState d:type="cDeltaString">ButtonUp</ButtonState>
					<Button d:type="cDeltaString">Key_K</Button>
					<ShiftButton d:type="cDeltaString">Shift</ShiftButton>
					<Axis d:type="cDeltaString">NoAxis</Axis>
					<Name d:type="cDeltaString">DecreaseControlStop</Name>
					<Parameter d:type="cDeltaString">PravaPoz</Parameter>
					<NewState d:type="sInt32">0</NewState>
				</iInputMapper-cInputMapEntry>
				<iInputMapper-cInputMapEntry d:id="52401">
					<State d:type="sInt32">0</State>
					<Device d:type="cDeltaString">Keyboard</Device>
					<ButtonState d:type="cDeltaString">ButtonDown</ButtonState>
					<Button d:type="cDeltaString">Key_O</Button>
					<ShiftButton d:type="cDeltaString">NoShift</ShiftButton>
					<Axis d:type="cDeltaString">NoAxis</Axis>
					<Name d:type="cDeltaString">IncreaseControlStart</Name>
					<Parameter d:type="cDeltaString">OsvetleniVozu</Parameter>
					<NewState d:type="sInt32">0</NewState>
				</iInputMapper-cInputMapEntry>
				<iInputMapper-cInputMapEntry d:id="52411">
					<State d:type="sInt32">0</State>
					<Device d:type="cDeltaString">Keyboard</Device>
					<ButtonState d:type="cDeltaString">ButtonUp</ButtonState>
					<Button d:type="cDeltaString">Key_O</Button>
					<ShiftButton d:type="cDeltaString">NoShift</ShiftButton>
					<Axis d:type="cDeltaString">NoAxis</Axis>
					<Name d:type="cDeltaString">IncreaseControlStop</Name>
					<Parameter d:type="cDeltaString">OsvetleniVozu</Parameter>
					<NewState d:type="sInt32">0</NewState>
				</iInputMapper-cInputMapEntry>
				<iInputMapper-cInputMapEntry d:id="52421">
					<State d:type="sInt32">0</State>
					<Device d:type="cDeltaString">Keyboard</Device>
					<ButtonState d:type="cDeltaString">ButtonDown</ButtonState>
					<Button d:type="cDeltaString">Key_O</Button>
					<ShiftButton d:type="cDeltaString">Shift</ShiftButton>
					<Axis d:type="cDeltaString">NoAxis</Axis>
					<Name d:type="cDeltaString">DecreaseControlStart</Name>
					<Parameter d:type="cDeltaString">OsvetleniVozu</Parameter>
					<NewState d:type="sInt32">0</NewState>
				</iInputMapper-cInputMapEntry>
				<iInputMapper-cInputMapEntry d:id="52431">
					<State d:type="sInt32">0</State>
					<Device d:type="cDeltaString">Keyboard</Device>
					<ButtonState d:type="cDeltaString">ButtonUp</ButtonState>
					<Button d:type="cDeltaString">Key_O</Button>
					<ShiftButton d:type="cDeltaString">Shift</ShiftButton>
					<Axis d:type="cDeltaString">NoAxis</Axis>
					<Name d:type="cDeltaString">DecreaseControlStop</Name>
					<Parameter d:type="cDeltaString">OsvetleniVozu</Parameter>
					<NewState d:type="sInt32">0</NewState>
				</iInputMapper-cInputMapEntry>
				<iInputMapper-cInputMapEntry d:id="52441">
					<State d:type="sInt32">0</State>
					<Device d:type="cDeltaString">Keyboard</Device>
					<ButtonState d:type="cDeltaString">ButtonDown</ButtonState>
					<Button d:type="cDeltaString">Key_L</Button>
					<ShiftButton d:type="cDeltaString">NoShift</ShiftButton>
					<Axis d:type="cDeltaString">NoAxis</Axis>
					<Name d:type="cDeltaString">IncreaseControlStart</Name>
					<Parameter d:type="cDeltaString">OsvetleniKabiny</Parameter>
					<NewState d:type="sInt32">0</NewState>
				</iInputMapper-cInputMapEntry>
				<iInputMapper-cInputMapEntry d:id="52451">
					<State d:type="sInt32">0</State>
					<Device d:type="cDeltaString">Keyboard</Device>
					<ButtonState d:type="cDeltaString">ButtonUp</ButtonState>
					<Button d:type="cDeltaString">Key_L</Button>
					<ShiftButton d:type="cDeltaString">NoShift</ShiftButton>
					<Axis d:type="cDeltaString">NoAxis</Axis>
					<Name d:type="cDeltaString">IncreaseControlStop</Name>
					<Parameter d:type="cDeltaString">OsvetleniKabiny</Parameter>
					<NewState d:type="sInt32">0</NewState>
				</iInputMapper-cInputMapEntry>
				<iInputMapper-cInputMapEntry d:id="52461">
					<State d:type="sInt32">0</State>
					<Device d:type="cDeltaString">Keyboard</Device>
					<ButtonState d:type="cDeltaString">ButtonDown</ButtonState>
					<Button d:type="cDeltaString">Key_L</Button>
					<ShiftButton d:type="cDeltaString">Shift</ShiftButton>
					<Axis d:type="cDeltaString">NoAxis</Axis>
					<Name d:type="cDeltaString">DecreaseControlStart</Name>
					<Parameter d:type="cDeltaString">OsvetleniKabiny</Parameter>
					<NewState d:type="sInt32">0</NewState>
				</iInputMapper-cInputMapEntry>
				<iInputMapper-cInputMapEntry d:id="52471">
					<State d:type="sInt32">0</State>
					<Device d:type="cDeltaString">Keyboard</Device>
					<ButtonState d:type="cDeltaString">ButtonUp</ButtonState>
					<Button d:type="cDeltaString">Key_L</Button>
					<ShiftButton d:type="cDeltaString">Shift</ShiftButton>
					<Axis d:type="cDeltaString">NoAxis</Axis>
					<Name d:type="cDeltaString">DecreaseControlStop</Name>
					<Parameter d:type="cDeltaString">OsvetleniKabiny</Parameter>
					<NewState d:type="sInt32">0</NewState>
				</iInputMapper-cInputMapEntry>
				<iInputMapper-cInputMapEntry d:id="52481">
					<State d:type="sInt32">0</State>
					<Device d:type="cDeltaString">Keyboard</Device>
					<ButtonState d:type="cDeltaString">ButtonDown</ButtonState>
					<Button d:type="cDeltaString">Key_L</Button>
					<ShiftButton d:type="cDeltaString">Control</ShiftButton>
					<Axis d:type="cDeltaString">NoAxis</Axis>
					<Name d:type="cDeltaString">ToggleControl</Name>
					<Parameter d:type="cDeltaString">Picka</Parameter>
					<NewState d:type="sInt32">0</NewState>
				</iInputMapper-cInputMapEntry>
				<iInputMapper-cInputMapEntry d:id="52491">
					<State d:type="sInt32">0</State>
					<Device d:type="cDeltaString">Keyboard</Device>
					<ButtonState d:type="cDeltaString">ButtonDown</ButtonState>
					<Button d:type="cDeltaString">Key_B</Button>
					<ShiftButton d:type="cDeltaString">Shift_Control</ShiftButton>
					<Axis d:type="cDeltaString">NoAxis</Axis>
					<Name d:type="cDeltaString">ToggleControl</Name>
					<Parameter d:type="cDeltaString">Baterie</Parameter>
					<NewState d:type="sInt32">0</NewState>
				</iInputMapper-cInputMapEntry>
				<iInputMapper-cInputMapEntry d:id="52501">
					<State d:type="sInt32">0</State>
					<Device d:type="cDeltaString">Keyboard</Device>
					<ButtonState d:type="cDeltaString">ButtonDown</ButtonState>
					<Button d:type="cDeltaString">Key_Q</Button>
					<ShiftButton d:type="cDeltaString">Shift_Control</ShiftButton>
					<Axis d:type="cDeltaString">NoAxis</Axis>
					<Name d:type="cDeltaString">ToggleControl</Name>
					<Parameter d:type="cDeltaString">JeZivakZap</Parameter>
					<NewState d:type="sInt32">0</NewState>
				</iInputMapper-cInputMapEntry>
				<iInputMapper-cInputMapEntry d:id="52511">
					<State d:type="sInt32">0</State>
					<Device d:type="cDeltaString">Keyboard</Device>
					<ButtonState d:type="cDeltaString">ButtonDown</ButtonState>
					<Button d:type="cDeltaString">Key_Space</Button>
					<ShiftButton d:type="cDeltaString">NoShift</ShiftButton>
					<Axis d:type="cDeltaString">NoAxis</Axis>
					<Name d:type="cDeltaString">IncreaseControlStart</Name>
					<Parameter d:type="cDeltaString">ZivakReset</Parameter>
					<NewState d:type="sInt32">0</NewState>
				</iInputMapper-cInputMapEntry>
				<iInputMapper-cInputMapEntry d:id="52521">
					<State d:type="sInt32">0</State>
					<Device d:type="cDeltaString">Keyboard</Device>
					<ButtonState d:type="cDeltaString">ButtonUp</ButtonState>
					<Button d:type="cDeltaString">Key_Space</Button>
					<ShiftButton d:type="cDeltaString">NoShift</ShiftButton>
					<Axis d:type="cDeltaString">NoAxis</Axis>
					<Name d:type="cDeltaString">DecreaseControlStart</Name>
					<Parameter d:type="cDeltaString">ZivakReset</Parameter>
					<NewState d:type="sInt32">0</NewState>
				</iInputMapper-cInputMapEntry>
				<iInputMapper-cInputMapEntry d:id="52531">
					<State d:type="sInt32">0</State>
					<Device d:type="cDeltaString">Keyboard</Device>
					<ButtonState d:type="cDeltaString">ButtonDown</ButtonState>
					<Button d:type="cDeltaString">Key_End</Button>
					<ShiftButton d:type="cDeltaString">Shift</ShiftButton>
					<Axis d:type="cDeltaString">NoAxis</Axis>
					<Name d:type="cDeltaString">ToggleControl</Name>
					<Parameter d:type="cDeltaString">JeNouzovyRadic</Parameter>
					<NewState d:type="sInt32">0</NewState>
				</iInputMapper-cInputMapEntry>
				<iInputMapper-cInputMapEntry d:id="52541">
					<State d:type="sInt32">0</State>
					<Device d:type="cDeltaString">Keyboard</Device>
					<ButtonState d:type="cDeltaString">ButtonDown</ButtonState>
					<Button d:type="cDeltaString">Key_Z</Button>
					<ShiftButton d:type="cDeltaString">NoShift</ShiftButton>
					<Axis d:type="cDeltaString">NoAxis</Axis>
					<Name d:type="cDeltaString">IncreaseControlStart</Name>
					<Parameter d:type="cDeltaString">VirtualStartup</Parameter>
					<NewState d:type="sInt32">0</NewState>
				</iInputMapper-cInputMapEntry>
				<iInputMapper-cInputMapEntry d:id="52551">
					<State d:type="sInt32">0</State>
					<Device d:type="cDeltaString">Keyboard</Device>
					<ButtonState d:type="cDeltaString">ButtonUp</ButtonState>
					<Button d:type="cDeltaString">Key_Z</Button>
					<ShiftButton d:type="cDeltaString">NoShift</ShiftButton>
					<Axis d:type="cDeltaString">NoAxis</Axis>
					<Name d:type="cDeltaString">IncreaseControlStop</Name>
					<Parameter d:type="cDeltaString">VirtualStartup</Parameter>
					<NewState d:type="sInt32">0</NewState>
				</iInputMapper-cInputMapEntry>
				<iInputMapper-cInputMapEntry d:id="52561">
					<State d:type="sInt32">0</State>
					<Device d:type="cDeltaString">Keyboard</Device>
					<ButtonState d:type="cDeltaString">ButtonDown</ButtonState>
					<Button d:type="cDeltaString">Key_Z</Button>
					<ShiftButton d:type="cDeltaString">Shift</ShiftButton>
					<Axis d:type="cDeltaString">NoAxis</Axis>
					<Name d:type="cDeltaString">DecreaseControlStart</Name>
					<Parameter d:type="cDeltaString">VirtualStartup</Parameter>
					<NewState d:type="sInt32">0</NewState>
				</iInputMapper-cInputMapEntry>
				<iInputMapper-cInputMapEntry d:id="52571">
					<State d:type="sInt32">0</State>
					<Device d:type="cDeltaString">Keyboard</Device>
					<ButtonState d:type="cDeltaString">ButtonDown</ButtonState>
					<Button d:type="cDeltaString">Key_Z</Button>
					<ShiftButton d:type="cDeltaString">NoShift</ShiftButton>
					<Axis d:type="cDeltaString">NoAxis</Axis>
					<Name d:type="cDeltaString">DecreaseControlStop</Name>
					<Parameter d:type="cDeltaString">VirtualStartup</Parameter>
					<NewState d:type="sInt32">0</NewState>
				</iInputMapper-cInputMapEntry>
				<iInputMapper-cInputMapEntry d:id="52581">
					<State d:type="sInt32">0</State>
					<Device d:type="cDeltaString">Keyboard</Device>
					<ButtonState d:type="cDeltaString">ButtonDown</ButtonState>
					<Button d:type="cDeltaString">Key_Z</Button>
					<ShiftButton d:type="cDeltaString">Control</ShiftButton>
					<Axis d:type="cDeltaString">NoAxis</Axis>
					<Name d:type="cDeltaString">ToggleControl</Name>
					<Parameter d:type="cDeltaString">vlozklic</Parameter>
					<NewState d:type="sInt32">0</NewState>
				</iInputMapper-cInputMapEntry>
				<iInputMapper-cInputMapEntry d:id="52591">
					<State d:type="sInt32">0</State>
					<Device d:type="cDeltaString">Keyboard</Device>
					<ButtonState d:type="cDeltaString">ButtonDown</ButtonState>
					<Button d:type="cDeltaString">Key_Z</Button>
					<ShiftButton d:type="cDeltaString">Shift_Control</ShiftButton>
					<Axis d:type="cDeltaString">NoAxis</Axis>
					<Name d:type="cDeltaString">ToggleControl</Name>
					<Parameter d:type="cDeltaString">vytahniklic</Parameter>
					<NewState d:type="sInt32">0</NewState>
				</iInputMapper-cInputMapEntry>
				<iInputMapper-cInputMapEntry d:id="52601">
					<State d:type="sInt32">0</State>
					<Device d:type="cDeltaString">Keyboard</Device>
					<ButtonState d:type="cDeltaString">ButtonDown</ButtonState>
					<Button d:type="cDeltaString">Key_E</Button>
					<ShiftButton d:type="cDeltaString">NoShift</ShiftButton>
					<Axis d:type="cDeltaString">NoAxis</Axis>
					<Name d:type="cDeltaString">IncreaseControlStart</Name>
					<Parameter d:type="cDeltaString">RozProud</Parameter>
					<NewState d:type="sInt32">0</NewState>
				</iInputMapper-cInputMapEntry>
				<iInputMapper-cInputMapEntry d:id="52611">
					<State d:type="sInt32">0</State>
					<Device d:type="cDeltaString">Keyboard</Device>
					<ButtonState d:type="cDeltaString">ButtonUp</ButtonState>
					<Button d:type="cDeltaString">Key_E</Button>
					<ShiftButton d:type="cDeltaString">NoShift</ShiftButton>
					<Axis d:type="cDeltaString">NoAxis</Axis>
					<Name d:type="cDeltaString">IncreaseControlStop</Name>
					<Parameter d:type="cDeltaString">RozProud</Parameter>
					<NewState d:type="sInt32">0</NewState>
				</iInputMapper-cInputMapEntry>
				<iInputMapper-cInputMapEntry d:id="52621">
					<State d:type="sInt32">0</State>
					<Device d:type="cDeltaString">Keyboard</Device>
					<ButtonState d:type="cDeltaString">ButtonDown</ButtonState>
					<Button d:type="cDeltaString">Key_E</Button>
					<ShiftButton d:type="cDeltaString">Shift</ShiftButton>
					<Axis d:type="cDeltaString">NoAxis</Axis>
					<Name d:type="cDeltaString">DecreaseControlStart</Name>
					<Parameter d:type="cDeltaString">RozProud</Parameter>
					<NewState d:type="sInt32">0</NewState>
				</iInputMapper-cInputMapEntry>
				<iInputMapper-cInputMapEntry d:id="52631">
					<State d:type="sInt32">0</State>
					<Device d:type="cDeltaString">Keyboard</Device>
					<ButtonState d:type="cDeltaString">ButtonUp</ButtonState>
					<Button d:type="cDeltaString">Key_E</Button>
					<ShiftButton d:type="cDeltaString">NoShift</ShiftButton>
					<Axis d:type="cDeltaString">NoAxis</Axis>
					<Name d:type="cDeltaString">IncreaseControlStop</Name>
					<Parameter d:type="cDeltaString">RozProud</Parameter>
					<NewState d:type="sInt32">0</NewState>
				</iInputMapper-cInputMapEntry>
				<iInputMapper-cInputMapEntry d:id="52641">
					<State d:type="sInt32">0</State>
					<Device d:type="cDeltaString">Keyboard</Device>
					<ButtonState d:type="cDeltaString">ButtonDown</ButtonState>
					<Button d:type="cDeltaString">Key_F12</Button>
					<ShiftButton d:type="cDeltaString">Shift_Control</ShiftButton>
					<Axis d:type="cDeltaString">NoAxis</Axis>
					<Name d:type="cDeltaString">ToggleControl</Name>
					<Parameter d:type="cDeltaString">FastStart</Parameter>
					<NewState d:type="sInt32">0</NewState>
				</iInputMapper-cInputMapEntry>
				<iInputMapper-cInputMapEntry d:id="52651">
					<State d:type="sInt32">0</State>
					<Device d:type="cDeltaString">Keyboard</Device>
					<ButtonState d:type="cDeltaString">ButtonDown</ButtonState>
					<Button d:type="cDeltaString">Key_SemiColon</Button>
					<ShiftButton d:type="cDeltaString">Shift_Control</ShiftButton>
					<Axis d:type="cDeltaString">NoAxis</Axis>
					<Name d:type="cDeltaString">ToggleControl</Name>
					<Parameter d:type="cDeltaString">ZamekBS2</Parameter>
					<NewState d:type="sInt32">0</NewState>
				</iInputMapper-cInputMapEntry>
				<iInputMapper-cInputMapEntry d:id="52661">
					<State d:type="sInt32">0</State>
					<Device d:type="cDeltaString">Keyboard</Device>
					<ButtonState d:type="cDeltaString">ButtonDown</ButtonState>
					<Button d:type="cDeltaString">Key_Return</Button>
					<ShiftButton d:type="cDeltaString">NoShift</ShiftButton>
					<Axis d:type="cDeltaString">NoAxis</Axis>
					<Name d:type="cDeltaString">IncreaseControlStart</Name>
					<Parameter d:type="cDeltaString">Matrosov</Parameter>
					<NewState d:type="sInt32">0</NewState>
				</iInputMapper-cInputMapEntry>
				<iInputMapper-cInputMapEntry d:id="52671">
					<State d:type="sInt32">0</State>
					<Device d:type="cDeltaString">Keyboard</Device>
					<ButtonState d:type="cDeltaString">ButtonDown</ButtonState>
					<Button d:type="cDeltaString">Key_Return</Button>
					<ShiftButton d:type="cDeltaString">NoShift</ShiftButton>
					<Axis d:type="cDeltaString">NoAxis</Axis>
					<Name d:type="cDeltaString">DecreaseControlStart</Name>
					<Parameter d:type="cDeltaString">Matrosov</Parameter>
					<NewState d:type="sInt32">0</NewState>
				</iInputMapper-cInputMapEntry>
				<iInputMapper-cInputMapEntry d:id="52681">
					<State d:type="sInt32">0</State>
					<Device d:type="cDeltaString">Keyboard</Device>
					<ButtonState d:type="cDeltaString">ButtonUp</ButtonState>
					<Button d:type="cDeltaString">Key_C</Button>
					<ShiftButton d:type="cDeltaString">Shift</ShiftButton>
					<Axis d:type="cDeltaString">NoAxis</Axis>
					<Name d:type="cDeltaString">DecreaseControlStart</Name>
					<Parameter d:type="cDeltaString">ButtonPojezdVDepu</Parameter>
					<NewState d:type="sInt32">0</NewState>
				</iInputMapper-cInputMapEntry>
				<iInputMapper-cInputMapEntry d:id="52691">
					<State d:type="sInt32">0</State>
					<Device d:type="cDeltaString">Keyboard</Device>
					<ButtonState d:type="cDeltaString">ButtonDown</ButtonState>
					<Button d:type="cDeltaString">Key_C</Button>
					<ShiftButton d:type="cDeltaString">Shift</ShiftButton>
					<Axis d:type="cDeltaString">NoAxis</Axis>
					<Name d:type="cDeltaString">IncreaseControlStart</Name>
					<Parameter d:type="cDeltaString">ButtonPojezdVDepu</Parameter>
					<NewState d:type="sInt32">0</NewState>
				</iInputMapper-cInputMapEntry>
				<iInputMapper-cInputMapEntry d:id="52701">
					<State d:type="sInt32">0</State>
					<Device d:type="cDeltaString">Keyboard</Device>
					<ButtonState d:type="cDeltaString">ButtonDown</ButtonState>
					<Button d:type="cDeltaString">Key_PageUp</Button>
					<ShiftButton d:type="cDeltaString">NoShift</ShiftButton>
					<Axis d:type="cDeltaString">NoAxis</Axis>
					<Name d:type="cDeltaString">IncreaseControlStart</Name>
					<Parameter d:type="cDeltaString">OknoL</Parameter>
					<NewState d:type="sInt32">0</NewState>
				</iInputMapper-cInputMapEntry>
				<iInputMapper-cInputMapEntry d:id="52711">
					<State d:type="sInt32">0</State>
					<Device d:type="cDeltaString">Keyboard</Device>
					<ButtonState d:type="cDeltaString">ButtonUp</ButtonState>
					<Button d:type="cDeltaString">Key_PageUp</Button>
					<ShiftButton d:type="cDeltaString">NoShift</ShiftButton>
					<Axis d:type="cDeltaString">NoAxis</Axis>
					<Name d:type="cDeltaString">IncreaseControlStop</Name>
					<Parameter d:type="cDeltaString">OknoL</Parameter>
					<NewState d:type="sInt32">0</NewState>
				</iInputMapper-cInputMapEntry>
				<iInputMapper-cInputMapEntry d:id="52721">
					<State d:type="sInt32">0</State>
					<Device d:type="cDeltaString">Keyboard</Device>
					<ButtonState d:type="cDeltaString">ButtonDown</ButtonState>
					<Button d:type="cDeltaString">Key_PageDown</Button>
					<ShiftButton d:type="cDeltaString">NoShift</ShiftButton>
					<Axis d:type="cDeltaString">NoAxis</Axis>
					<Name d:type="cDeltaString">DecreaseControlStart</Name>
					<Parameter d:type="cDeltaString">OknoL</Parameter>
					<NewState d:type="sInt32">0</NewState>
				</iInputMapper-cInputMapEntry>
				<iInputMapper-cInputMapEntry d:id="52731">
					<State d:type="sInt32">0</State>
					<Device d:type="cDeltaString">Keyboard</Device>
					<ButtonState d:type="cDeltaString">ButtonUp</ButtonState>
					<Button d:type="cDeltaString">Key_PageDown</Button>
					<ShiftButton d:type="cDeltaString">NoShift</ShiftButton>
					<Axis d:type="cDeltaString">NoAxis</Axis>
					<Name d:type="cDeltaString">DecreaseControlStop</Name>
					<Parameter d:type="cDeltaString">OknoL</Parameter>
					<NewState d:type="sInt32">0</NewState>
				</iInputMapper-cInputMapEntry>
				<iInputMapper-cInputMapEntry d:id="52741">
					<State d:type="sInt32">0</State>
					<Device d:type="cDeltaString">Keyboard</Device>
					<ButtonState d:type="cDeltaString">ButtonDown</ButtonState>
					<Button d:type="cDeltaString">Key_U</Button>
					<ShiftButton d:type="cDeltaString">NoShift</ShiftButton>
					<Axis d:type="cDeltaString">NoAxis</Axis>
					<Name d:type="cDeltaString">IncreaseControlStart</Name>
					<Parameter d:type="cDeltaString">DverePrepLevy</Parameter>
					<NewState d:type="sInt32">0</NewState>
				</iInputMapper-cInputMapEntry>
				<iInputMapper-cInputMapEntry d:id="52751">
					<State d:type="sInt32">0</State>
					<Device d:type="cDeltaString">Keyboard</Device>
					<ButtonState d:type="cDeltaString">ButtonUp</ButtonState>
					<Button d:type="cDeltaString">Key_U</Button>
					<ShiftButton d:type="cDeltaString">NoShift</ShiftButton>
					<Axis d:type="cDeltaString">NoAxis</Axis>
					<Name d:type="cDeltaString">IncreaseControlStop</Name>
					<Parameter d:type="cDeltaString">DverePrepLevy</Parameter>
					<NewState d:type="sInt32">0</NewState>
				</iInputMapper-cInputMapEntry>
				<iInputMapper-cInputMapEntry d:id="52761">
					<State d:type="sInt32">0</State>
					<Device d:type="cDeltaString">Keyboard</Device>
					<ButtonState d:type="cDeltaString">ButtonDown</ButtonState>
					<Button d:type="cDeltaString">Key_U</Button>
					<ShiftButton d:type="cDeltaString">Shift</ShiftButton>
					<Axis d:type="cDeltaString">NoAxis</Axis>
					<Name d:type="cDeltaString">DecreaseControlStart</Name>
					<Parameter d:type="cDeltaString">DverePrepLevy</Parameter>
					<NewState d:type="sInt32">0</NewState>
				</iInputMapper-cInputMapEntry>
				<iInputMapper-cInputMapEntry d:id="52771">
					<State d:type="sInt32">0</State>
					<Device d:type="cDeltaString">Keyboard</Device>
					<ButtonState d:type="cDeltaString">ButtonUp</ButtonState>
					<Button d:type="cDeltaString">Key_U</Button>
					<ShiftButton d:type="cDeltaString">Shift</ShiftButton>
					<Axis d:type="cDeltaString">NoAxis</Axis>
					<Name d:type="cDeltaString">DecreaseControlStop</Name>
					<Parameter d:type="cDeltaString">DverePrepLevy</Parameter>
					<NewState d:type="sInt32">0</NewState>
				</iInputMapper-cInputMapEntry>
				<iInputMapper-cInputMapEntry d:id="52781">
					<State d:type="sInt32">0</State>
					<Device d:type="cDeltaString">Keyboard</Device>
					<ButtonState d:type="cDeltaString">ButtonDown</ButtonState>
					<Button d:type="cDeltaString">Key_I</Button>
					<ShiftButton d:type="cDeltaString">NoShift</ShiftButton>
					<Axis d:type="cDeltaString">NoAxis</Axis>
					<Name d:type="cDeltaString">IncreaseControlStart</Name>
					<Parameter d:type="cDeltaString">DverePrepPravy</Parameter>
					<NewState d:type="sInt32">0</NewState>
				</iInputMapper-cInputMapEntry>
				<iInputMapper-cInputMapEntry d:id="52791">
					<State d:type="sInt32">0</State>
					<Device d:type="cDeltaString">Keyboard</Device>
					<ButtonState d:type="cDeltaString">ButtonUp</ButtonState>
					<Button d:type="cDeltaString">Key_I</Button>
					<ShiftButton d:type="cDeltaString">NoShift</ShiftButton>
					<Axis d:type="cDeltaString">NoAxis</Axis>
					<Name d:type="cDeltaString">IncreaseControlStop</Name>
					<Parameter d:type="cDeltaString">DverePrepPravy</Parameter>
					<NewState d:type="sInt32">0</NewState>
				</iInputMapper-cInputMapEntry>
				<iInputMapper-cInputMapEntry d:id="52801">
					<State d:type="sInt32">0</State>
					<Device d:type="cDeltaString">Keyboard</Device>
					<ButtonState d:type="cDeltaString">ButtonDown</ButtonState>
					<Button d:type="cDeltaString">Key_I</Button>
					<ShiftButton d:type="cDeltaString">Shift</ShiftButton>
					<Axis d:type="cDeltaString">NoAxis</Axis>
					<Name d:type="cDeltaString">DecreaseControlStart</Name>
					<Parameter d:type="cDeltaString">DverePrepPravy</Parameter>
					<NewState d:type="sInt32">0</NewState>
				</iInputMapper-cInputMapEntry>
				<iInputMapper-cInputMapEntry d:id="52811">
					<State d:type="sInt32">0</State>
					<Device d:type="cDeltaString">Keyboard</Device>
					<ButtonState d:type="cDeltaString">ButtonUp</ButtonState>
					<Button d:type="cDeltaString">Key_I</Button>
					<ShiftButton d:type="cDeltaString">Shift</ShiftButton>
					<Axis d:type="cDeltaString">NoAxis</Axis>
					<Name d:type="cDeltaString">DecreaseControlStop</Name>
					<Parameter d:type="cDeltaString">DverePrepPravy</Parameter>
					<NewState d:type="sInt32">0</NewState>
				</iInputMapper-cInputMapEntry>
				<iInputMapper-cInputMapEntry d:id="52821">
					<State d:type="sInt32">0</State>
					<Device d:type="cDeltaString">Keyboard</Device>
					<ButtonState d:type="cDeltaString">ButtonDown</ButtonState>
					<Button d:type="cDeltaString">Key_0</Button>
					<ShiftButton d:type="cDeltaString">Shift_Control</ShiftButton>
					<Axis d:type="cDeltaString">NoAxis</Axis>
					<Name d:type="cDeltaString">IncreaseControlStart</Name>
					<Parameter d:type="cDeltaString">Napoveda</Parameter>
					<NewState d:type="sInt32">0</NewState>
				</iInputMapper-cInputMapEntry>
				<iInputMapper-cInputMapEntry d:id="52831">
					<State d:type="sInt32">0</State>
					<Device d:type="cDeltaString">Keyboard</Device>
					<ButtonState d:type="cDeltaString">ButtonUp</ButtonState>
					<Button d:type="cDeltaString">Key_0</Button>
					<ShiftButton d:type="cDeltaString">Shift_Control</ShiftButton>
					<Axis d:type="cDeltaString">NoAxis</Axis>
					<Name d:type="cDeltaString">IncreaseControlStop</Name>
					<Parameter d:type="cDeltaString">Napoveda</Parameter>
					<NewState d:type="sInt32">0</NewState>
				</iInputMapper-cInputMapEntry>
				<iInputMapper-cInputMapEntry d:id="52841">
					<State d:type="sInt32">0</State>
					<Device d:type="cDeltaString">Keyboard</Device>
					<ButtonState d:type="cDeltaString">ButtonDown</ButtonState>
					<Button d:type="cDeltaString">NumPad_Subtract</Button>
					<ShiftButton d:type="cDeltaString">Control</ShiftButton>
					<Axis d:type="cDeltaString">NoAxis</Axis>
					<Name d:type="cDeltaString">IncreaseControlStart</Name>
					<Parameter d:type="cDeltaString">MSVdolu</Parameter>
					<NewState d:type="sInt32">0</NewState>
				</iInputMapper-cInputMapEntry>
				<iInputMapper-cInputMapEntry d:id="52851">
					<State d:type="sInt32">0</State>
					<Device d:type="cDeltaString">Keyboard</Device>
					<ButtonState d:type="cDeltaString">ButtonUp</ButtonState>
					<Button d:type="cDeltaString">NumPad_Subtract</Button>
					<ShiftButton d:type="cDeltaString">Control</ShiftButton>
					<Axis d:type="cDeltaString">NoAxis</Axis>
					<Name d:type="cDeltaString">DecreaseControlStart</Name>
					<Parameter d:type="cDeltaString">MSVdolu</Parameter>
					<NewState d:type="sInt32">0</NewState>
				</iInputMapper-cInputMapEntry>
				<iInputMapper-cInputMapEntry d:id="52861">
					<State d:type="sInt32">0</State>
					<Device d:type="cDeltaString">Keyboard</Device>
					<ButtonState d:type="cDeltaString">ButtonDown</ButtonState>
					<Button d:type="cDeltaString">NumPad_Add</Button>
					<ShiftButton d:type="cDeltaString">Control</ShiftButton>
					<Axis d:type="cDeltaString">NoAxis</Axis>
					<Name d:type="cDeltaString">IncreaseControlStart</Name>
					<Parameter d:type="cDeltaString">MSVnahoru</Parameter>
					<NewState d:type="sInt32">0</NewState>
				</iInputMapper-cInputMapEntry>
				<iInputMapper-cInputMapEntry d:id="52871">
					<State d:type="sInt32">0</State>
					<Device d:type="cDeltaString">Keyboard</Device>
					<ButtonState d:type="cDeltaString">ButtonUp</ButtonState>
					<Button d:type="cDeltaString">NumPad_Add</Button>
					<ShiftButton d:type="cDeltaString">Control</ShiftButton>
					<Axis d:type="cDeltaString">NoAxis</Axis>
					<Name d:type="cDeltaString">DecreaseControlStart</Name>
					<Parameter d:type="cDeltaString">MSVnahoru</Parameter>
					<NewState d:type="sInt32">0</NewState>
				</iInputMapper-cInputMapEntry>
				<iInputMapper-cInputMapEntry d:id="52881">
					<State d:type="sInt32">0</State>
					<Device d:type="cDeltaString">Keyboard</Device>
					<ButtonState d:type="cDeltaString">ButtonDown</ButtonState>
					<Button d:type="cDeltaString">NumPad_Divide</Button>
					<ShiftButton d:type="cDeltaString">Control</ShiftButton>
					<Axis d:type="cDeltaString">NoAxis</Axis>
					<Name d:type="cDeltaString">IncreaseControlStart</Name>
					<Parameter d:type="cDeltaString">MSVleva</Parameter>
					<NewState d:type="sInt32">0</NewState>
				</iInputMapper-cInputMapEntry>
				<iInputMapper-cInputMapEntry d:id="52891">
					<State d:type="sInt32">0</State>
					<Device d:type="cDeltaString">Keyboard</Device>
					<ButtonState d:type="cDeltaString">ButtonUp</ButtonState>
					<Button d:type="cDeltaString">NumPad_Divide</Button>
					<ShiftButton d:type="cDeltaString">Control</ShiftButton>
					<Axis d:type="cDeltaString">NoAxis</Axis>
					<Name d:type="cDeltaString">DecreaseControlStart</Name>
					<Parameter d:type="cDeltaString">MSVleva</Parameter>
					<NewState d:type="sInt32">0</NewState>
				</iInputMapper-cInputMapEntry>
				<iInputMapper-cInputMapEntry d:id="52901">
					<State d:type="sInt32">0</State>
					<Device d:type="cDeltaString">Keyboard</Device>
					<ButtonState d:type="cDeltaString">ButtonDown</ButtonState>
					<Button d:type="cDeltaString">NumPad_Multiply</Button>
					<ShiftButton d:type="cDeltaString">Control</ShiftButton>
					<Axis d:type="cDeltaString">NoAxis</Axis>
					<Name d:type="cDeltaString">IncreaseControlStart</Name>
					<Parameter d:type="cDeltaString">MSVprava</Parameter>
					<NewState d:type="sInt32">0</NewState>
				</iInputMapper-cInputMapEntry>
				<iInputMapper-cInputMapEntry d:id="52911">
					<State d:type="sInt32">0</State>
					<Device d:type="cDeltaString">Keyboard</Device>
					<ButtonState d:type="cDeltaString">ButtonUp</ButtonState>
					<Button d:type="cDeltaString">NumPad_Multiply</Button>
					<ShiftButton d:type="cDeltaString">Control</ShiftButton>
					<Axis d:type="cDeltaString">NoAxis</Axis>
					<Name d:type="cDeltaString">DecreaseControlStart</Name>
					<Parameter d:type="cDeltaString">MSVprava</Parameter>
					<NewState d:type="sInt32">0</NewState>
				</iInputMapper-cInputMapEntry>
				<iInputMapper-cInputMapEntry d:id="52921">
					<State d:type="sInt32">0</State>
					<Device d:type="cDeltaString">Keyboard</Device>
					<ButtonState d:type="cDeltaString">ButtonDown</ButtonState>
					<Button d:type="cDeltaString">NumPad_Enter</Button>
					<ShiftButton d:type="cDeltaString">Control</ShiftButton>
					<Axis d:type="cDeltaString">NoAxis</Axis>
					<Name d:type="cDeltaString">IncreaseControlStart</Name>
					<Parameter d:type="cDeltaString">MSVok</Parameter>
					<NewState d:type="sInt32">0</NewState>
				</iInputMapper-cInputMapEntry>
				<iInputMapper-cInputMapEntry d:id="52931">
					<State d:type="sInt32">0</State>
					<Device d:type="cDeltaString">Keyboard</Device>
					<ButtonState d:type="cDeltaString">ButtonUp</ButtonState>
					<Button d:type="cDeltaString">NumPad_Enter</Button>
					<ShiftButton d:type="cDeltaString">Control</ShiftButton>
					<Axis d:type="cDeltaString">NoAxis</Axis>
					<Name d:type="cDeltaString">DecreaseControlStart</Name>
					<Parameter d:type="cDeltaString">MSVok</Parameter>
					<NewState d:type="sInt32">0</NewState>
				</iInputMapper-cInputMapEntry>
			</Map>
			<MapItem />
		</cInputMapperBlueprint>
	</Blueprint>
</cBlueprintLoader>
