<?xml version="1.0" encoding="utf-8"?>
<cBlueprintLoader xmlns:d="http://www.kuju.com/TnT/2003/Delta" d:version="1.0">
	<Blueprint>
		<cInputMapperBlueprint xmlns:d="http://www.kuju.com/TnT/2003/Delta" d:version="1.0">
			<RemapperName d:type="cDeltaString">460_expert</RemapperName>
			<Map>
				<iInputMapper-cInputMapEntry d:id="13913">
					<State d:type="sInt32">0</State>
					<Device d:type="cDeltaString">Keyboard</Device>
					<ButtonState d:type="cDeltaString">ButtonDown</ButtonState>
					<Button d:type="cDeltaString">Key_P</Button>
					<ShiftButton d:type="cDeltaString">NoShift</ShiftButton>
					<Axis d:type="cDeltaString">NoAxis</Axis>
					<Name d:type="cDeltaString">ToggleControl</Name>
					<Parameter d:type="cDeltaString">VirtualPantographControl</Parameter>
					<NewState d:type="sInt32">0</NewState>
				</iInputMapper-cInputMapEntry>
				<iInputMapper-cInputMapEntry d:id="13923">
					<State d:type="sInt32">0</State>
					<Device d:type="cDeltaString">Keyboard</Device>
					<ButtonState d:type="cDeltaString">ButtonDown</ButtonState>
					<Button d:type="cDeltaString">Key_D</Button>
					<ShiftButton d:type="cDeltaString">NoShift</ShiftButton>
					<Axis d:type="cDeltaString">NoAxis</Axis>
					<Name d:type="cDeltaString">DecreaseControlStart</Name>
					<Parameter d:type="cDeltaString">RadicNouzovy</Parameter>
					<NewState d:type="sInt32">0</NewState>
				</iInputMapper-cInputMapEntry>
				<iInputMapper-cInputMapEntry d:id="13933">
					<State d:type="sInt32">0</State>
					<Device d:type="cDeltaString">Keyboard</Device>
					<ButtonState d:type="cDeltaString">ButtonDown</ButtonState>
					<Button d:type="cDeltaString">Key_D</Button>
					<ShiftButton d:type="cDeltaString">NoShift</ShiftButton>
					<Axis d:type="cDeltaString">NoAxis</Axis>
					<Name d:type="cDeltaString">DecreaseControlStart</Name>
					<Parameter d:type="cDeltaString">VirtualThrottleAndBrake</Parameter>
					<NewState d:type="sInt32">0</NewState>
				</iInputMapper-cInputMapEntry>
				<iInputMapper-cInputMapEntry d:id="13943">
					<State d:type="sInt32">0</State>
					<Device d:type="cDeltaString">Keyboard</Device>
					<ButtonState d:type="cDeltaString">ButtonUp</ButtonState>
					<Button d:type="cDeltaString">Key_D</Button>
					<ShiftButton d:type="cDeltaString">NoShift</ShiftButton>
					<Axis d:type="cDeltaString">NoAxis</Axis>
					<Name d:type="cDeltaString">DecreaseControlStop</Name>
					<Parameter d:type="cDeltaString">RadicNouzovy</Parameter>
					<NewState d:type="sInt32">0</NewState>
				</iInputMapper-cInputMapEntry>
				<iInputMapper-cInputMapEntry d:id="13953">
					<State d:type="sInt32">0</State>
					<Device d:type="cDeltaString">Keyboard</Device>
					<ButtonState d:type="cDeltaString">ButtonUp</ButtonState>
					<Button d:type="cDeltaString">Key_D</Button>
					<ShiftButton d:type="cDeltaString">NoShift</ShiftButton>
					<Axis d:type="cDeltaString">NoAxis</Axis>
					<Name d:type="cDeltaString">DecreaseControlStop</Name>
					<Parameter d:type="cDeltaString">VirtualThrottleAndBrake</Parameter>
					<NewState d:type="sInt32">0</NewState>
				</iInputMapper-cInputMapEntry>
				<iInputMapper-cInputMapEntry d:id="13963">
					<State d:type="sInt32">0</State>
					<Device d:type="cDeltaString">Keyboard</Device>
					<ButtonState d:type="cDeltaString">ButtonDown</ButtonState>
					<Button d:type="cDeltaString">Key_A</Button>
					<ShiftButton d:type="cDeltaString">NoShift</ShiftButton>
					<Axis d:type="cDeltaString">NoAxis</Axis>
					<Name d:type="cDeltaString">IncreaseControlStart</Name>
					<Parameter d:type="cDeltaString">RadicNouzovy</Parameter>
					<NewState d:type="sInt32">0</NewState>
				</iInputMapper-cInputMapEntry>
				<iInputMapper-cInputMapEntry d:id="13973">
					<State d:type="sInt32">0</State>
					<Device d:type="cDeltaString">Keyboard</Device>
					<ButtonState d:type="cDeltaString">ButtonDown</ButtonState>
					<Button d:type="cDeltaString">Key_A</Button>
					<ShiftButton d:type="cDeltaString">NoShift</ShiftButton>
					<Axis d:type="cDeltaString">NoAxis</Axis>
					<Name d:type="cDeltaString">IncreaseControlStart</Name>
					<Parameter d:type="cDeltaString">VirtualThrottleAndBrake</Parameter>
					<NewState d:type="sInt32">0</NewState>
				</iInputMapper-cInputMapEntry>
				<iInputMapper-cInputMapEntry d:id="13983">
					<State d:type="sInt32">0</State>
					<Device d:type="cDeltaString">Keyboard</Device>
					<ButtonState d:type="cDeltaString">ButtonUp</ButtonState>
					<Button d:type="cDeltaString">Key_A</Button>
					<ShiftButton d:type="cDeltaString">NoShift</ShiftButton>
					<Axis d:type="cDeltaString">NoAxis</Axis>
					<Name d:type="cDeltaString">IncreaseControlStop</Name>
					<Parameter d:type="cDeltaString">RadicNouzovy</Parameter>
					<NewState d:type="sInt32">0</NewState>
				</iInputMapper-cInputMapEntry>
				<iInputMapper-cInputMapEntry d:id="13993">
					<State d:type="sInt32">0</State>
					<Device d:type="cDeltaString">Keyboard</Device>
					<ButtonState d:type="cDeltaString">ButtonUp</ButtonState>
					<Button d:type="cDeltaString">Key_A</Button>
					<ShiftButton d:type="cDeltaString">NoShift</ShiftButton>
					<Axis d:type="cDeltaString">NoAxis</Axis>
					<Name d:type="cDeltaString">IncreaseControlStop</Name>
					<Parameter d:type="cDeltaString">VirtualThrottleAndBrake</Parameter>
					<NewState d:type="sInt32">0</NewState>
				</iInputMapper-cInputMapEntry>
				<iInputMapper-cInputMapEntry d:id="14003">
					<State d:type="sInt32">0</State>
					<Device d:type="cDeltaString">Keyboard</Device>
					<ButtonState d:type="cDeltaString">ButtonDown</ButtonState>
					<Button d:type="cDeltaString">Key_W</Button>
					<ShiftButton d:type="cDeltaString">NoShift</ShiftButton>
					<Axis d:type="cDeltaString">NoAxis</Axis>
					<Name d:type="cDeltaString">IncreaseControlStart</Name>
					<Parameter d:type="cDeltaString">VypinacHlavy</Parameter>
					<NewState d:type="sInt32">0</NewState>
				</iInputMapper-cInputMapEntry>
				<iInputMapper-cInputMapEntry d:id="14013">
					<State d:type="sInt32">0</State>
					<Device d:type="cDeltaString">Keyboard</Device>
					<ButtonState d:type="cDeltaString">ButtonDown</ButtonState>
					<Button d:type="cDeltaString">Key_W</Button>
					<ShiftButton d:type="cDeltaString">NoShift</ShiftButton>
					<Axis d:type="cDeltaString">NoAxis</Axis>
					<Name d:type="cDeltaString">IncreaseControlStart</Name>
					<Parameter d:type="cDeltaString">UserVirtualReverser</Parameter>
					<NewState d:type="sInt32">0</NewState>
				</iInputMapper-cInputMapEntry>
				<iInputMapper-cInputMapEntry d:id="14023">
					<State d:type="sInt32">0</State>
					<Device d:type="cDeltaString">Keyboard</Device>
					<ButtonState d:type="cDeltaString">ButtonUp</ButtonState>
					<Button d:type="cDeltaString">Key_W</Button>
					<ShiftButton d:type="cDeltaString">NoShift</ShiftButton>
					<Axis d:type="cDeltaString">NoAxis</Axis>
					<Name d:type="cDeltaString">IncreaseControlStop</Name>
					<Parameter d:type="cDeltaString">VypinacHlavy</Parameter>
					<NewState d:type="sInt32">0</NewState>
				</iInputMapper-cInputMapEntry>
				<iInputMapper-cInputMapEntry d:id="14033">
					<State d:type="sInt32">0</State>
					<Device d:type="cDeltaString">Keyboard</Device>
					<ButtonState d:type="cDeltaString">ButtonUp</ButtonState>
					<Button d:type="cDeltaString">Key_W</Button>
					<ShiftButton d:type="cDeltaString">NoShift</ShiftButton>
					<Axis d:type="cDeltaString">NoAxis</Axis>
					<Name d:type="cDeltaString">IncreaseControlStop</Name>
					<Parameter d:type="cDeltaString">UserVirtualReverser</Parameter>
					<NewState d:type="sInt32">0</NewState>
				</iInputMapper-cInputMapEntry>
				<iInputMapper-cInputMapEntry d:id="14043">
					<State d:type="sInt32">0</State>
					<Device d:type="cDeltaString">Keyboard</Device>
					<ButtonState d:type="cDeltaString">ButtonDown</ButtonState>
					<Button d:type="cDeltaString">Key_S</Button>
					<ShiftButton d:type="cDeltaString">NoShift</ShiftButton>
					<Axis d:type="cDeltaString">NoAxis</Axis>
					<Name d:type="cDeltaString">DecreaseControlStart</Name>
					<Parameter d:type="cDeltaString">VypinacHlavy</Parameter>
					<NewState d:type="sInt32">0</NewState>
				</iInputMapper-cInputMapEntry>
				<iInputMapper-cInputMapEntry d:id="14053">
					<State d:type="sInt32">0</State>
					<Device d:type="cDeltaString">Keyboard</Device>
					<ButtonState d:type="cDeltaString">ButtonDown</ButtonState>
					<Button d:type="cDeltaString">Key_S</Button>
					<ShiftButton d:type="cDeltaString">NoShift</ShiftButton>
					<Axis d:type="cDeltaString">NoAxis</Axis>
					<Name d:type="cDeltaString">DecreaseControlStart</Name>
					<Parameter d:type="cDeltaString">UserVirtualReverser</Parameter>
					<NewState d:type="sInt32">0</NewState>
				</iInputMapper-cInputMapEntry>
				<iInputMapper-cInputMapEntry d:id="14063">
					<State d:type="sInt32">0</State>
					<Device d:type="cDeltaString">Keyboard</Device>
					<ButtonState d:type="cDeltaString">ButtonUp</ButtonState>
					<Button d:type="cDeltaString">Key_S</Button>
					<ShiftButton d:type="cDeltaString">NoShift</ShiftButton>
					<Axis d:type="cDeltaString">NoAxis</Axis>
					<Name d:type="cDeltaString">DecreaseControlStop</Name>
					<Parameter d:type="cDeltaString">VypinacHlavy</Parameter>
					<NewState d:type="sInt32">0</NewState>
				</iInputMapper-cInputMapEntry>
				<iInputMapper-cInputMapEntry d:id="14073">
					<State d:type="sInt32">0</State>
					<Device d:type="cDeltaString">Keyboard</Device>
					<ButtonState d:type="cDeltaString">ButtonUp</ButtonState>
					<Button d:type="cDeltaString">Key_S</Button>
					<ShiftButton d:type="cDeltaString">NoShift</ShiftButton>
					<Axis d:type="cDeltaString">NoAxis</Axis>
					<Name d:type="cDeltaString">DecreaseControlStop</Name>
					<Parameter d:type="cDeltaString">UserVirtualReverser</Parameter>
					<NewState d:type="sInt32">0</NewState>
				</iInputMapper-cInputMapEntry>
				<iInputMapper-cInputMapEntry d:id="14083">
					<State d:type="sInt32">0</State>
					<Device d:type="cDeltaString">Keyboard</Device>
					<ButtonState d:type="cDeltaString">ButtonDown</ButtonState>
					<Button d:type="cDeltaString">Key_Left_Bracket</Button>
					<ShiftButton d:type="cDeltaString">NoShift</ShiftButton>
					<Axis d:type="cDeltaString">NoAxis</Axis>
					<Name d:type="cDeltaString">DecreaseControlStart</Name>
					<Parameter d:type="cDeltaString">EngineBrakeControl</Parameter>
					<NewState d:type="sInt32">0</NewState>
				</iInputMapper-cInputMapEntry>
				<iInputMapper-cInputMapEntry d:id="14093">
					<State d:type="sInt32">0</State>
					<Device d:type="cDeltaString">Keyboard</Device>
					<ButtonState d:type="cDeltaString">ButtonUp</ButtonState>
					<Button d:type="cDeltaString">Key_Left_Bracket</Button>
					<ShiftButton d:type="cDeltaString">NoShift</ShiftButton>
					<Axis d:type="cDeltaString">NoAxis</Axis>
					<Name d:type="cDeltaString">DecreaseControlStop</Name>
					<Parameter d:type="cDeltaString">EngineBrakeControl</Parameter>
					<NewState d:type="sInt32">0</NewState>
				</iInputMapper-cInputMapEntry>
				<iInputMapper-cInputMapEntry d:id="14103">
					<State d:type="sInt32">0</State>
					<Device d:type="cDeltaString">Keyboard</Device>
					<ButtonState d:type="cDeltaString">ButtonDown</ButtonState>
					<Button d:type="cDeltaString">Key_Right_Bracket</Button>
					<ShiftButton d:type="cDeltaString">NoShift</ShiftButton>
					<Axis d:type="cDeltaString">NoAxis</Axis>
					<Name d:type="cDeltaString">IncreaseControlStart</Name>
					<Parameter d:type="cDeltaString">EngineBrakeControl</Parameter>
					<NewState d:type="sInt32">0</NewState>
				</iInputMapper-cInputMapEntry>
				<iInputMapper-cInputMapEntry d:id="14113">
					<State d:type="sInt32">0</State>
					<Device d:type="cDeltaString">Keyboard</Device>
					<ButtonState d:type="cDeltaString">ButtonUp</ButtonState>
					<Button d:type="cDeltaString">Key_Right_Bracket</Button>
					<ShiftButton d:type="cDeltaString">NoShift</ShiftButton>
					<Axis d:type="cDeltaString">NoAxis</Axis>
					<Name d:type="cDeltaString">IncreaseControlStop</Name>
					<Parameter d:type="cDeltaString">EngineBrakeControl</Parameter>
					<NewState d:type="sInt32">0</NewState>
				</iInputMapper-cInputMapEntry>
				<iInputMapper-cInputMapEntry d:id="14123">
					<State d:type="sInt32">0</State>
					<Device d:type="cDeltaString">Keyboard</Device>
					<ButtonState d:type="cDeltaString">ButtonDown</ButtonState>
					<Button d:type="cDeltaString">Key_SemiColon</Button>
					<ShiftButton d:type="cDeltaString">NoShift</ShiftButton>
					<Axis d:type="cDeltaString">NoAxis</Axis>
					<Name d:type="cDeltaString">DecreaseControlStart</Name>
					<Parameter d:type="cDeltaString">VirtualBrake</Parameter>
					<NewState d:type="sInt32">0</NewState>
				</iInputMapper-cInputMapEntry>
				<iInputMapper-cInputMapEntry d:id="14133">
					<State d:type="sInt32">0</State>
					<Device d:type="cDeltaString">Keyboard</Device>
					<ButtonState d:type="cDeltaString">ButtonUp</ButtonState>
					<Button d:type="cDeltaString">Key_SemiColon</Button>
					<ShiftButton d:type="cDeltaString">NoShift</ShiftButton>
					<Axis d:type="cDeltaString">NoAxis</Axis>
					<Name d:type="cDeltaString">DecreaseControlStop</Name>
					<Parameter d:type="cDeltaString">VirtualBrake</Parameter>
					<NewState d:type="sInt32">0</NewState>
				</iInputMapper-cInputMapEntry>
				<iInputMapper-cInputMapEntry d:id="14143">
					<State d:type="sInt32">0</State>
					<Device d:type="cDeltaString">Keyboard</Device>
					<ButtonState d:type="cDeltaString">ButtonDown</ButtonState>
					<Button d:type="cDeltaString">Key_Apostophe</Button>
					<ShiftButton d:type="cDeltaString">NoShift</ShiftButton>
					<Axis d:type="cDeltaString">NoAxis</Axis>
					<Name d:type="cDeltaString">IncreaseControlStart</Name>
					<Parameter d:type="cDeltaString">VirtualBrake</Parameter>
					<NewState d:type="sInt32">0</NewState>
				</iInputMapper-cInputMapEntry>
				<iInputMapper-cInputMapEntry d:id="14153">
					<State d:type="sInt32">0</State>
					<Device d:type="cDeltaString">Keyboard</Device>
					<ButtonState d:type="cDeltaString">ButtonUp</ButtonState>
					<Button d:type="cDeltaString">Key_Apostophe</Button>
					<ShiftButton d:type="cDeltaString">NoShift</ShiftButton>
					<Axis d:type="cDeltaString">NoAxis</Axis>
					<Name d:type="cDeltaString">IncreaseControlStop</Name>
					<Parameter d:type="cDeltaString">VirtualBrake</Parameter>
					<NewState d:type="sInt32">0</NewState>
				</iInputMapper-cInputMapEntry>
				<iInputMapper-cInputMapEntry d:id="14163">
					<State d:type="sInt32">0</State>
					<Device d:type="cDeltaString">Keyboard</Device>
					<ButtonState d:type="cDeltaString">ButtonDown</ButtonState>
					<Button d:type="cDeltaString">Key_H</Button>
					<ShiftButton d:type="cDeltaString">NoShift</ShiftButton>
					<Axis d:type="cDeltaString">NoAxis</Axis>
					<Name d:type="cDeltaString">IncreaseControlStart</Name>
					<Parameter d:type="cDeltaString">VirtualHeadlights</Parameter>
					<NewState d:type="sInt32">0</NewState>
				</iInputMapper-cInputMapEntry>
				<iInputMapper-cInputMapEntry d:id="14173">
					<State d:type="sInt32">0</State>
					<Device d:type="cDeltaString">Keyboard</Device>
					<ButtonState d:type="cDeltaString">ButtonUp</ButtonState>
					<Button d:type="cDeltaString">Key_H</Button>
					<ShiftButton d:type="cDeltaString">NoShift</ShiftButton>
					<Axis d:type="cDeltaString">NoAxis</Axis>
					<Name d:type="cDeltaString">IncreaseControlStop</Name>
					<Parameter d:type="cDeltaString">VirtualHeadlights</Parameter>
					<NewState d:type="sInt32">0</NewState>
				</iInputMapper-cInputMapEntry>
				<iInputMapper-cInputMapEntry d:id="14183">
					<State d:type="sInt32">0</State>
					<Device d:type="cDeltaString">Keyboard</Device>
					<ButtonState d:type="cDeltaString">ButtonDown</ButtonState>
					<Button d:type="cDeltaString">Key_H</Button>
					<ShiftButton d:type="cDeltaString">Shift</ShiftButton>
					<Axis d:type="cDeltaString">NoAxis</Axis>
					<Name d:type="cDeltaString">DecreaseControlStart</Name>
					<Parameter d:type="cDeltaString">VirtualHeadlights</Parameter>
					<NewState d:type="sInt32">0</NewState>
				</iInputMapper-cInputMapEntry>
				<iInputMapper-cInputMapEntry d:id="14193">
					<State d:type="sInt32">0</State>
					<Device d:type="cDeltaString">Keyboard</Device>
					<ButtonState d:type="cDeltaString">ButtonUp</ButtonState>
					<Button d:type="cDeltaString">Key_H</Button>
					<ShiftButton d:type="cDeltaString">Shift</ShiftButton>
					<Axis d:type="cDeltaString">NoAxis</Axis>
					<Name d:type="cDeltaString">DecreaseControlStop</Name>
					<Parameter d:type="cDeltaString">VirtualHeadlights</Parameter>
					<NewState d:type="sInt32">0</NewState>
				</iInputMapper-cInputMapEntry>
				<iInputMapper-cInputMapEntry d:id="14203">
					<State d:type="sInt32">0</State>
					<Device d:type="cDeltaString">Keyboard</Device>
					<ButtonState d:type="cDeltaString">ButtonDown</ButtonState>
					<Button d:type="cDeltaString">Key_V</Button>
					<ShiftButton d:type="cDeltaString">NoShift</ShiftButton>
					<Axis d:type="cDeltaString">NoAxis</Axis>
					<Name d:type="cDeltaString">IncreaseControlStart</Name>
					<Parameter d:type="cDeltaString">steracePrep</Parameter>
					<NewState d:type="sInt32">0</NewState>
				</iInputMapper-cInputMapEntry>
				<iInputMapper-cInputMapEntry d:id="14213">
					<State d:type="sInt32">0</State>
					<Device d:type="cDeltaString">Keyboard</Device>
					<ButtonState d:type="cDeltaString">ButtonUp</ButtonState>
					<Button d:type="cDeltaString">Key_V</Button>
					<ShiftButton d:type="cDeltaString">NoShift</ShiftButton>
					<Axis d:type="cDeltaString">NoAxis</Axis>
					<Name d:type="cDeltaString">IncreaseControlStop</Name>
					<Parameter d:type="cDeltaString">steracePrep</Parameter>
					<NewState d:type="sInt32">0</NewState>
				</iInputMapper-cInputMapEntry>
				<iInputMapper-cInputMapEntry d:id="14223">
					<State d:type="sInt32">0</State>
					<Device d:type="cDeltaString">Keyboard</Device>
					<ButtonState d:type="cDeltaString">ButtonDown</ButtonState>
					<Button d:type="cDeltaString">Key_V</Button>
					<ShiftButton d:type="cDeltaString">Shift</ShiftButton>
					<Axis d:type="cDeltaString">NoAxis</Axis>
					<Name d:type="cDeltaString">DecreaseControlStart</Name>
					<Parameter d:type="cDeltaString">steracePrep</Parameter>
					<NewState d:type="sInt32">0</NewState>
				</iInputMapper-cInputMapEntry>
				<iInputMapper-cInputMapEntry d:id="14233">
					<State d:type="sInt32">0</State>
					<Device d:type="cDeltaString">Keyboard</Device>
					<ButtonState d:type="cDeltaString">ButtonUp</ButtonState>
					<Button d:type="cDeltaString">Key_V</Button>
					<ShiftButton d:type="cDeltaString">Shift</ShiftButton>
					<Axis d:type="cDeltaString">NoAxis</Axis>
					<Name d:type="cDeltaString">DecreaseControlStop</Name>
					<Parameter d:type="cDeltaString">steracePrep</Parameter>
					<NewState d:type="sInt32">0</NewState>
				</iInputMapper-cInputMapEntry>
				<iInputMapper-cInputMapEntry d:id="14243">
					<State d:type="sInt32">0</State>
					<Device d:type="cDeltaString">Keyboard</Device>
					<ButtonState d:type="cDeltaString">ButtonDown</ButtonState>
					<Button d:type="cDeltaString">Key_B</Button>
					<ShiftButton d:type="cDeltaString">NoShift</ShiftButton>
					<Axis d:type="cDeltaString">NoAxis</Axis>
					<Name d:type="cDeltaString">IncreaseControlStart</Name>
					<Parameter d:type="cDeltaString">Horn</Parameter>
					<NewState d:type="sInt32">0</NewState>
				</iInputMapper-cInputMapEntry>
				<iInputMapper-cInputMapEntry d:id="14253">
					<State d:type="sInt32">0</State>
					<Device d:type="cDeltaString">Keyboard</Device>
					<ButtonState d:type="cDeltaString">ButtonUp</ButtonState>
					<Button d:type="cDeltaString">Key_B</Button>
					<ShiftButton d:type="cDeltaString">NoShift</ShiftButton>
					<Axis d:type="cDeltaString">NoAxis</Axis>
					<Name d:type="cDeltaString">DecreaseControlStart</Name>
					<Parameter d:type="cDeltaString">Horn</Parameter>
					<NewState d:type="sInt32">0</NewState>
				</iInputMapper-cInputMapEntry>
				<iInputMapper-cInputMapEntry d:id="14263">
					<State d:type="sInt32">0</State>
					<Device d:type="cDeltaString">Keyboard</Device>
					<ButtonState d:type="cDeltaString">ButtonDown</ButtonState>
					<Button d:type="cDeltaString">Key_N</Button>
					<ShiftButton d:type="cDeltaString">NoShift</ShiftButton>
					<Axis d:type="cDeltaString">NoAxis</Axis>
					<Name d:type="cDeltaString">IncreaseControlStart</Name>
					<Parameter d:type="cDeltaString">Bell</Parameter>
					<NewState d:type="sInt32">0</NewState>
				</iInputMapper-cInputMapEntry>
				<iInputMapper-cInputMapEntry d:id="14273">
					<State d:type="sInt32">0</State>
					<Device d:type="cDeltaString">Keyboard</Device>
					<ButtonState d:type="cDeltaString">ButtonUp</ButtonState>
					<Button d:type="cDeltaString">Key_N</Button>
					<ShiftButton d:type="cDeltaString">NoShift</ShiftButton>
					<Axis d:type="cDeltaString">NoAxis</Axis>
					<Name d:type="cDeltaString">DecreaseControlStart</Name>
					<Parameter d:type="cDeltaString">Bell</Parameter>
					<NewState d:type="sInt32">0</NewState>
				</iInputMapper-cInputMapEntry>
				<iInputMapper-cInputMapEntry d:id="14283">
					<State d:type="sInt32">0</State>
					<Device d:type="cDeltaString">Keyboard</Device>
					<ButtonState d:type="cDeltaString">ButtonDown</ButtonState>
					<Button d:type="cDeltaString">Key_M</Button>
					<ShiftButton d:type="cDeltaString">NoShift</ShiftButton>
					<Axis d:type="cDeltaString">NoAxis</Axis>
					<Name d:type="cDeltaString">IncreaseControlStart</Name>
					<Parameter d:type="cDeltaString">VolbaPozicKonecCelo</Parameter>
					<NewState d:type="sInt32">0</NewState>
				</iInputMapper-cInputMapEntry>
				<iInputMapper-cInputMapEntry d:id="14293">
					<State d:type="sInt32">0</State>
					<Device d:type="cDeltaString">Keyboard</Device>
					<ButtonState d:type="cDeltaString">ButtonUp</ButtonState>
					<Button d:type="cDeltaString">Key_M</Button>
					<ShiftButton d:type="cDeltaString">NoShift</ShiftButton>
					<Axis d:type="cDeltaString">NoAxis</Axis>
					<Name d:type="cDeltaString">IncreaseControlStop</Name>
					<Parameter d:type="cDeltaString">VolbaPozicKonecCelo</Parameter>
					<NewState d:type="sInt32">0</NewState>
				</iInputMapper-cInputMapEntry>
				<iInputMapper-cInputMapEntry d:id="14303">
					<State d:type="sInt32">0</State>
					<Device d:type="cDeltaString">Keyboard</Device>
					<ButtonState d:type="cDeltaString">ButtonDown</ButtonState>
					<Button d:type="cDeltaString">Key_M</Button>
					<ShiftButton d:type="cDeltaString">Shift</ShiftButton>
					<Axis d:type="cDeltaString">NoAxis</Axis>
					<Name d:type="cDeltaString">DecreaseControlStart</Name>
					<Parameter d:type="cDeltaString">VolbaPozicKonecCelo</Parameter>
					<NewState d:type="sInt32">0</NewState>
				</iInputMapper-cInputMapEntry>
				<iInputMapper-cInputMapEntry d:id="14313">
					<State d:type="sInt32">0</State>
					<Device d:type="cDeltaString">Keyboard</Device>
					<ButtonState d:type="cDeltaString">ButtonUp</ButtonState>
					<Button d:type="cDeltaString">Key_M</Button>
					<ShiftButton d:type="cDeltaString">Shift</ShiftButton>
					<Axis d:type="cDeltaString">NoAxis</Axis>
					<Name d:type="cDeltaString">DecreaseControlStop</Name>
					<Parameter d:type="cDeltaString">VolbaPozicKonecCelo</Parameter>
					<NewState d:type="sInt32">0</NewState>
				</iInputMapper-cInputMapEntry>
				<iInputMapper-cInputMapEntry d:id="14323">
					<State d:type="sInt32">0</State>
					<Device d:type="cDeltaString">Keyboard</Device>
					<ButtonState d:type="cDeltaString">ButtonDown</ButtonState>
					<Button d:type="cDeltaString">Key_J</Button>
					<ShiftButton d:type="cDeltaString">NoShift</ShiftButton>
					<Axis d:type="cDeltaString">NoAxis</Axis>
					<Name d:type="cDeltaString">IncreaseControlStart</Name>
					<Parameter d:type="cDeltaString">LevaPoz</Parameter>
					<NewState d:type="sInt32">0</NewState>
				</iInputMapper-cInputMapEntry>
				<iInputMapper-cInputMapEntry d:id="14333">
					<State d:type="sInt32">0</State>
					<Device d:type="cDeltaString">Keyboard</Device>
					<ButtonState d:type="cDeltaString">ButtonUp</ButtonState>
					<Button d:type="cDeltaString">Key_J</Button>
					<ShiftButton d:type="cDeltaString">NoShift</ShiftButton>
					<Axis d:type="cDeltaString">NoAxis</Axis>
					<Name d:type="cDeltaString">IncreaseControlStop</Name>
					<Parameter d:type="cDeltaString">LevaPoz</Parameter>
					<NewState d:type="sInt32">0</NewState>
				</iInputMapper-cInputMapEntry>
				<iInputMapper-cInputMapEntry d:id="14343">
					<State d:type="sInt32">0</State>
					<Device d:type="cDeltaString">Keyboard</Device>
					<ButtonState d:type="cDeltaString">ButtonDown</ButtonState>
					<Button d:type="cDeltaString">Key_J</Button>
					<ShiftButton d:type="cDeltaString">Shift</ShiftButton>
					<Axis d:type="cDeltaString">NoAxis</Axis>
					<Name d:type="cDeltaString">DecreaseControlStart</Name>
					<Parameter d:type="cDeltaString">LevaPoz</Parameter>
					<NewState d:type="sInt32">0</NewState>
				</iInputMapper-cInputMapEntry>
				<iInputMapper-cInputMapEntry d:id="14353">
					<State d:type="sInt32">0</State>
					<Device d:type="cDeltaString">Keyboard</Device>
					<ButtonState d:type="cDeltaString">ButtonUp</ButtonState>
					<Button d:type="cDeltaString">Key_J</Button>
					<ShiftButton d:type="cDeltaString">Shift</ShiftButton>
					<Axis d:type="cDeltaString">NoAxis</Axis>
					<Name d:type="cDeltaString">DecreaseControlStop</Name>
					<Parameter d:type="cDeltaString">LevaPoz</Parameter>
					<NewState d:type="sInt32">0</NewState>
				</iInputMapper-cInputMapEntry>
				<iInputMapper-cInputMapEntry d:id="14363">
					<State d:type="sInt32">0</State>
					<Device d:type="cDeltaString">Keyboard</Device>
					<ButtonState d:type="cDeltaString">ButtonDown</ButtonState>
					<Button d:type="cDeltaString">Key_K</Button>
					<ShiftButton d:type="cDeltaString">NoShift</ShiftButton>
					<Axis d:type="cDeltaString">NoAxis</Axis>
					<Name d:type="cDeltaString">IncreaseControlStart</Name>
					<Parameter d:type="cDeltaString">PravaPoz</Parameter>
					<NewState d:type="sInt32">0</NewState>
				</iInputMapper-cInputMapEntry>
				<iInputMapper-cInputMapEntry d:id="14373">
					<State d:type="sInt32">0</State>
					<Device d:type="cDeltaString">Keyboard</Device>
					<ButtonState d:type="cDeltaString">ButtonUp</ButtonState>
					<Button d:type="cDeltaString">Key_K</Button>
					<ShiftButton d:type="cDeltaString">NoShift</ShiftButton>
					<Axis d:type="cDeltaString">NoAxis</Axis>
					<Name d:type="cDeltaString">IncreaseControlStop</Name>
					<Parameter d:type="cDeltaString">PravaPoz</Parameter>
					<NewState d:type="sInt32">0</NewState>
				</iInputMapper-cInputMapEntry>
				<iInputMapper-cInputMapEntry d:id="14383">
					<State d:type="sInt32">0</State>
					<Device d:type="cDeltaString">Keyboard</Device>
					<ButtonState d:type="cDeltaString">ButtonDown</ButtonState>
					<Button d:type="cDeltaString">Key_K</Button>
					<ShiftButton d:type="cDeltaString">Shift</ShiftButton>
					<Axis d:type="cDeltaString">NoAxis</Axis>
					<Name d:type="cDeltaString">DecreaseControlStart</Name>
					<Parameter d:type="cDeltaString">PravaPoz</Parameter>
					<NewState d:type="sInt32">0</NewState>
				</iInputMapper-cInputMapEntry>
				<iInputMapper-cInputMapEntry d:id="14393">
					<State d:type="sInt32">0</State>
					<Device d:type="cDeltaString">Keyboard</Device>
					<ButtonState d:type="cDeltaString">ButtonUp</ButtonState>
					<Button d:type="cDeltaString">Key_K</Button>
					<ShiftButton d:type="cDeltaString">Shift</ShiftButton>
					<Axis d:type="cDeltaString">NoAxis</Axis>
					<Name d:type="cDeltaString">DecreaseControlStop</Name>
					<Parameter d:type="cDeltaString">PravaPoz</Parameter>
					<NewState d:type="sInt32">0</NewState>
				</iInputMapper-cInputMapEntry>
				<iInputMapper-cInputMapEntry d:id="14403">
					<State d:type="sInt32">0</State>
					<Device d:type="cDeltaString">Keyboard</Device>
					<ButtonState d:type="cDeltaString">ButtonDown</ButtonState>
					<Button d:type="cDeltaString">Key_O</Button>
					<ShiftButton d:type="cDeltaString">NoShift</ShiftButton>
					<Axis d:type="cDeltaString">NoAxis</Axis>
					<Name d:type="cDeltaString">IncreaseControlStart</Name>
					<Parameter d:type="cDeltaString">OsvetleniVozu</Parameter>
					<NewState d:type="sInt32">0</NewState>
				</iInputMapper-cInputMapEntry>
				<iInputMapper-cInputMapEntry d:id="14413">
					<State d:type="sInt32">0</State>
					<Device d:type="cDeltaString">Keyboard</Device>
					<ButtonState d:type="cDeltaString">ButtonUp</ButtonState>
					<Button d:type="cDeltaString">Key_O</Button>
					<ShiftButton d:type="cDeltaString">NoShift</ShiftButton>
					<Axis d:type="cDeltaString">NoAxis</Axis>
					<Name d:type="cDeltaString">IncreaseControlStop</Name>
					<Parameter d:type="cDeltaString">OsvetleniVozu</Parameter>
					<NewState d:type="sInt32">0</NewState>
				</iInputMapper-cInputMapEntry>
				<iInputMapper-cInputMapEntry d:id="14423">
					<State d:type="sInt32">0</State>
					<Device d:type="cDeltaString">Keyboard</Device>
					<ButtonState d:type="cDeltaString">ButtonDown</ButtonState>
					<Button d:type="cDeltaString">Key_O</Button>
					<ShiftButton d:type="cDeltaString">Shift</ShiftButton>
					<Axis d:type="cDeltaString">NoAxis</Axis>
					<Name d:type="cDeltaString">DecreaseControlStart</Name>
					<Parameter d:type="cDeltaString">OsvetleniVozu</Parameter>
					<NewState d:type="sInt32">0</NewState>
				</iInputMapper-cInputMapEntry>
				<iInputMapper-cInputMapEntry d:id="14433">
					<State d:type="sInt32">0</State>
					<Device d:type="cDeltaString">Keyboard</Device>
					<ButtonState d:type="cDeltaString">ButtonUp</ButtonState>
					<Button d:type="cDeltaString">Key_O</Button>
					<ShiftButton d:type="cDeltaString">Shift</ShiftButton>
					<Axis d:type="cDeltaString">NoAxis</Axis>
					<Name d:type="cDeltaString">DecreaseControlStop</Name>
					<Parameter d:type="cDeltaString">OsvetleniVozu</Parameter>
					<NewState d:type="sInt32">0</NewState>
				</iInputMapper-cInputMapEntry>
				<iInputMapper-cInputMapEntry d:id="14443">
					<State d:type="sInt32">0</State>
					<Device d:type="cDeltaString">Keyboard</Device>
					<ButtonState d:type="cDeltaString">ButtonDown</ButtonState>
					<Button d:type="cDeltaString">Key_L</Button>
					<ShiftButton d:type="cDeltaString">NoShift</ShiftButton>
					<Axis d:type="cDeltaString">NoAxis</Axis>
					<Name d:type="cDeltaString">IncreaseControlStart</Name>
					<Parameter d:type="cDeltaString">OsvetleniKabiny</Parameter>
					<NewState d:type="sInt32">0</NewState>
				</iInputMapper-cInputMapEntry>
				<iInputMapper-cInputMapEntry d:id="14453">
					<State d:type="sInt32">0</State>
					<Device d:type="cDeltaString">Keyboard</Device>
					<ButtonState d:type="cDeltaString">ButtonUp</ButtonState>
					<Button d:type="cDeltaString">Key_L</Button>
					<ShiftButton d:type="cDeltaString">NoShift</ShiftButton>
					<Axis d:type="cDeltaString">NoAxis</Axis>
					<Name d:type="cDeltaString">IncreaseControlStop</Name>
					<Parameter d:type="cDeltaString">OsvetleniKabiny</Parameter>
					<NewState d:type="sInt32">0</NewState>
				</iInputMapper-cInputMapEntry>
				<iInputMapper-cInputMapEntry d:id="14463">
					<State d:type="sInt32">0</State>
					<Device d:type="cDeltaString">Keyboard</Device>
					<ButtonState d:type="cDeltaString">ButtonDown</ButtonState>
					<Button d:type="cDeltaString">Key_L</Button>
					<ShiftButton d:type="cDeltaString">Shift</ShiftButton>
					<Axis d:type="cDeltaString">NoAxis</Axis>
					<Name d:type="cDeltaString">DecreaseControlStart</Name>
					<Parameter d:type="cDeltaString">OsvetleniKabiny</Parameter>
					<NewState d:type="sInt32">0</NewState>
				</iInputMapper-cInputMapEntry>
				<iInputMapper-cInputMapEntry d:id="14473">
					<State d:type="sInt32">0</State>
					<Device d:type="cDeltaString">Keyboard</Device>
					<ButtonState d:type="cDeltaString">ButtonUp</ButtonState>
					<Button d:type="cDeltaString">Key_L</Button>
					<ShiftButton d:type="cDeltaString">Shift</ShiftButton>
					<Axis d:type="cDeltaString">NoAxis</Axis>
					<Name d:type="cDeltaString">DecreaseControlStop</Name>
					<Parameter d:type="cDeltaString">OsvetleniKabiny</Parameter>
					<NewState d:type="sInt32">0</NewState>
				</iInputMapper-cInputMapEntry>
				<iInputMapper-cInputMapEntry d:id="14483">
					<State d:type="sInt32">0</State>
					<Device d:type="cDeltaString">Keyboard</Device>
					<ButtonState d:type="cDeltaString">ButtonDown</ButtonState>
					<Button d:type="cDeltaString">Key_L</Button>
					<ShiftButton d:type="cDeltaString">Control</ShiftButton>
					<Axis d:type="cDeltaString">NoAxis</Axis>
					<Name d:type="cDeltaString">ToggleControl</Name>
					<Parameter d:type="cDeltaString">Picka</Parameter>
					<NewState d:type="sInt32">0</NewState>
				</iInputMapper-cInputMapEntry>
				<iInputMapper-cInputMapEntry d:id="14493">
					<State d:type="sInt32">0</State>
					<Device d:type="cDeltaString">Keyboard</Device>
					<ButtonState d:type="cDeltaString">ButtonDown</ButtonState>
					<Button d:type="cDeltaString">Key_B</Button>
					<ShiftButton d:type="cDeltaString">Control</ShiftButton>
					<Axis d:type="cDeltaString">NoAxis</Axis>
					<Name d:type="cDeltaString">IncreaseControlStart</Name>
					<Parameter d:type="cDeltaString">Baterie</Parameter>
					<NewState d:type="sInt32">0</NewState>
				</iInputMapper-cInputMapEntry>
				<iInputMapper-cInputMapEntry d:id="14503">
					<State d:type="sInt32">0</State>
					<Device d:type="cDeltaString">Keyboard</Device>
					<ButtonState d:type="cDeltaString">ButtonDown</ButtonState>
					<Button d:type="cDeltaString">Key_B</Button>
					<ShiftButton d:type="cDeltaString">Control</ShiftButton>
					<Axis d:type="cDeltaString">NoAxis</Axis>
					<Name d:type="cDeltaString">IncreaseControlStop</Name>
					<Parameter d:type="cDeltaString">Baterie</Parameter>
					<NewState d:type="sInt32">0</NewState>
				</iInputMapper-cInputMapEntry>
				<iInputMapper-cInputMapEntry d:id="14513">
					<State d:type="sInt32">0</State>
					<Device d:type="cDeltaString">Keyboard</Device>
					<ButtonState d:type="cDeltaString">ButtonDown</ButtonState>
					<Button d:type="cDeltaString">Key_B</Button>
					<ShiftButton d:type="cDeltaString">Shift_Control</ShiftButton>
					<Axis d:type="cDeltaString">NoAxis</Axis>
					<Name d:type="cDeltaString">DecreaseControlStart</Name>
					<Parameter d:type="cDeltaString">Baterie</Parameter>
					<NewState d:type="sInt32">0</NewState>
				</iInputMapper-cInputMapEntry>
				<iInputMapper-cInputMapEntry d:id="14523">
					<State d:type="sInt32">0</State>
					<Device d:type="cDeltaString">Keyboard</Device>
					<ButtonState d:type="cDeltaString">ButtonUp</ButtonState>
					<Button d:type="cDeltaString">Key_B</Button>
					<ShiftButton d:type="cDeltaString">Shift_Control</ShiftButton>
					<Axis d:type="cDeltaString">NoAxis</Axis>
					<Name d:type="cDeltaString">DecreaseControlStop</Name>
					<Parameter d:type="cDeltaString">Baterie</Parameter>
					<NewState d:type="sInt32">0</NewState>
				</iInputMapper-cInputMapEntry>
				<iInputMapper-cInputMapEntry d:id="14533">
					<State d:type="sInt32">0</State>
					<Device d:type="cDeltaString">Keyboard</Device>
					<ButtonState d:type="cDeltaString">ButtonDown</ButtonState>
					<Button d:type="cDeltaString">Key_Space</Button>
					<ShiftButton d:type="cDeltaString">NoShift</ShiftButton>
					<Axis d:type="cDeltaString">NoAxis</Axis>
					<Name d:type="cDeltaString">IncreaseControlStart</Name>
					<Parameter d:type="cDeltaString">ZivakReset</Parameter>
					<NewState d:type="sInt32">0</NewState>
				</iInputMapper-cInputMapEntry>
				<iInputMapper-cInputMapEntry d:id="14543">
					<State d:type="sInt32">0</State>
					<Device d:type="cDeltaString">Keyboard</Device>
					<ButtonState d:type="cDeltaString">ButtonUp</ButtonState>
					<Button d:type="cDeltaString">Key_Space</Button>
					<ShiftButton d:type="cDeltaString">NoShift</ShiftButton>
					<Axis d:type="cDeltaString">NoAxis</Axis>
					<Name d:type="cDeltaString">DecreaseControlStart</Name>
					<Parameter d:type="cDeltaString">ZivakReset</Parameter>
					<NewState d:type="sInt32">0</NewState>
				</iInputMapper-cInputMapEntry>
				<iInputMapper-cInputMapEntry d:id="14553">
					<State d:type="sInt32">0</State>
					<Device d:type="cDeltaString">Keyboard</Device>
					<ButtonState d:type="cDeltaString">ButtonDown</ButtonState>
					<Button d:type="cDeltaString">Key_End</Button>
					<ShiftButton d:type="cDeltaString">Shift</ShiftButton>
					<Axis d:type="cDeltaString">NoAxis</Axis>
					<Name d:type="cDeltaString">ToggleControl</Name>
					<Parameter d:type="cDeltaString">JeNouzovyRadic</Parameter>
					<NewState d:type="sInt32">0</NewState>
				</iInputMapper-cInputMapEntry>
				<iInputMapper-cInputMapEntry d:id="14563">
					<State d:type="sInt32">0</State>
					<Device d:type="cDeltaString">Keyboard</Device>
					<ButtonState d:type="cDeltaString">ButtonDown</ButtonState>
					<Button d:type="cDeltaString">Key_Delete</Button>
					<ShiftButton d:type="cDeltaString">Shift</ShiftButton>
					<Axis d:type="cDeltaString">NoAxis</Axis>
					<Name d:type="cDeltaString">ToggleControl</Name>
					<Parameter d:type="cDeltaString">JeSmerVeVypinaci</Parameter>
					<NewState d:type="sInt32">0</NewState>
				</iInputMapper-cInputMapEntry>
				<iInputMapper-cInputMapEntry d:id="14573">
					<State d:type="sInt32">0</State>
					<Device d:type="cDeltaString">Keyboard</Device>
					<ButtonState d:type="cDeltaString">ButtonDown</ButtonState>
					<Button d:type="cDeltaString">Key_Z</Button>
					<ShiftButton d:type="cDeltaString">NoShift</ShiftButton>
					<Axis d:type="cDeltaString">NoAxis</Axis>
					<Name d:type="cDeltaString">IncreaseControlStart</Name>
					<Parameter d:type="cDeltaString">VirtualStartup</Parameter>
					<NewState d:type="sInt32">0</NewState>
				</iInputMapper-cInputMapEntry>
				<iInputMapper-cInputMapEntry d:id="14583">
					<State d:type="sInt32">0</State>
					<Device d:type="cDeltaString">Keyboard</Device>
					<ButtonState d:type="cDeltaString">ButtonUp</ButtonState>
					<Button d:type="cDeltaString">Key_Z</Button>
					<ShiftButton d:type="cDeltaString">NoShift</ShiftButton>
					<Axis d:type="cDeltaString">NoAxis</Axis>
					<Name d:type="cDeltaString">IncreaseControlStop</Name>
					<Parameter d:type="cDeltaString">VirtualStartup</Parameter>
					<NewState d:type="sInt32">0</NewState>
				</iInputMapper-cInputMapEntry>
				<iInputMapper-cInputMapEntry d:id="14593">
					<State d:type="sInt32">0</State>
					<Device d:type="cDeltaString">Keyboard</Device>
					<ButtonState d:type="cDeltaString">ButtonDown</ButtonState>
					<Button d:type="cDeltaString">Key_Z</Button>
					<ShiftButton d:type="cDeltaString">Shift</ShiftButton>
					<Axis d:type="cDeltaString">NoAxis</Axis>
					<Name d:type="cDeltaString">DecreaseControlStart</Name>
					<Parameter d:type="cDeltaString">VirtualStartup</Parameter>
					<NewState d:type="sInt32">0</NewState>
				</iInputMapper-cInputMapEntry>
				<iInputMapper-cInputMapEntry d:id="14603">
					<State d:type="sInt32">0</State>
					<Device d:type="cDeltaString">Keyboard</Device>
					<ButtonState d:type="cDeltaString">ButtonUp</ButtonState>
					<Button d:type="cDeltaString">Key_Z</Button>
					<ShiftButton d:type="cDeltaString">Shift</ShiftButton>
					<Axis d:type="cDeltaString">NoAxis</Axis>
					<Name d:type="cDeltaString">DecreaseControlStop</Name>
					<Parameter d:type="cDeltaString">VirtualStartup</Parameter>
					<NewState d:type="sInt32">0</NewState>
				</iInputMapper-cInputMapEntry>
				<iInputMapper-cInputMapEntry d:id="14613">
					<State d:type="sInt32">0</State>
					<Device d:type="cDeltaString">Keyboard</Device>
					<ButtonState d:type="cDeltaString">ButtonDown</ButtonState>
					<Button d:type="cDeltaString">Key_Z</Button>
					<ShiftButton d:type="cDeltaString">Control</ShiftButton>
					<Axis d:type="cDeltaString">NoAxis</Axis>
					<Name d:type="cDeltaString">ToggleControl</Name>
					<Parameter d:type="cDeltaString">vlozklic</Parameter>
					<NewState d:type="sInt32">0</NewState>
				</iInputMapper-cInputMapEntry>
				<iInputMapper-cInputMapEntry d:id="14623">
					<State d:type="sInt32">0</State>
					<Device d:type="cDeltaString">Keyboard</Device>
					<ButtonState d:type="cDeltaString">ButtonDown</ButtonState>
					<Button d:type="cDeltaString">Key_Z</Button>
					<ShiftButton d:type="cDeltaString">Shift_Control</ShiftButton>
					<Axis d:type="cDeltaString">NoAxis</Axis>
					<Name d:type="cDeltaString">ToggleControl</Name>
					<Parameter d:type="cDeltaString">vytahniklic</Parameter>
					<NewState d:type="sInt32">0</NewState>
				</iInputMapper-cInputMapEntry>
				<iInputMapper-cInputMapEntry d:id="14633">
					<State d:type="sInt32">0</State>
					<Device d:type="cDeltaString">Keyboard</Device>
					<ButtonState d:type="cDeltaString">ButtonDown</ButtonState>
					<Button d:type="cDeltaString">Key_PageUp</Button>
					<ShiftButton d:type="cDeltaString">NoShift</ShiftButton>
					<Axis d:type="cDeltaString">NoAxis</Axis>
					<Name d:type="cDeltaString">IncreaseControlStart</Name>
					<Parameter d:type="cDeltaString">RozProud</Parameter>
					<NewState d:type="sInt32">0</NewState>
				</iInputMapper-cInputMapEntry>
				<iInputMapper-cInputMapEntry d:id="14643">
					<State d:type="sInt32">0</State>
					<Device d:type="cDeltaString">Keyboard</Device>
					<ButtonState d:type="cDeltaString">ButtonUp</ButtonState>
					<Button d:type="cDeltaString">Key_PageUp</Button>
					<ShiftButton d:type="cDeltaString">NoShift</ShiftButton>
					<Axis d:type="cDeltaString">NoAxis</Axis>
					<Name d:type="cDeltaString">IncreaseControlStop</Name>
					<Parameter d:type="cDeltaString">RozProud</Parameter>
					<NewState d:type="sInt32">0</NewState>
				</iInputMapper-cInputMapEntry>
				<iInputMapper-cInputMapEntry d:id="14653">
					<State d:type="sInt32">0</State>
					<Device d:type="cDeltaString">Keyboard</Device>
					<ButtonState d:type="cDeltaString">ButtonDown</ButtonState>
					<Button d:type="cDeltaString">Key_PageDown</Button>
					<ShiftButton d:type="cDeltaString">NoShift</ShiftButton>
					<Axis d:type="cDeltaString">NoAxis</Axis>
					<Name d:type="cDeltaString">DecreaseControlStart</Name>
					<Parameter d:type="cDeltaString">RozProud</Parameter>
					<NewState d:type="sInt32">0</NewState>
				</iInputMapper-cInputMapEntry>
				<iInputMapper-cInputMapEntry d:id="14663">
					<State d:type="sInt32">0</State>
					<Device d:type="cDeltaString">Keyboard</Device>
					<ButtonState d:type="cDeltaString">ButtonUp</ButtonState>
					<Button d:type="cDeltaString">Key_PageDown</Button>
					<ShiftButton d:type="cDeltaString">NoShift</ShiftButton>
					<Axis d:type="cDeltaString">NoAxis</Axis>
					<Name d:type="cDeltaString">IncreaseControlStop</Name>
					<Parameter d:type="cDeltaString">RozProud</Parameter>
					<NewState d:type="sInt32">0</NewState>
				</iInputMapper-cInputMapEntry>
				<iInputMapper-cInputMapEntry d:id="14673">
					<State d:type="sInt32">0</State>
					<Device d:type="cDeltaString">Keyboard</Device>
					<ButtonState d:type="cDeltaString">ButtonDown</ButtonState>
					<Button d:type="cDeltaString">Key_F12</Button>
					<ShiftButton d:type="cDeltaString">Shift_Control</ShiftButton>
					<Axis d:type="cDeltaString">NoAxis</Axis>
					<Name d:type="cDeltaString">ToggleControl</Name>
					<Parameter d:type="cDeltaString">FastStart</Parameter>
					<NewState d:type="sInt32">0</NewState>
				</iInputMapper-cInputMapEntry>
				<iInputMapper-cInputMapEntry d:id="14683">
					<State d:type="sInt32">0</State>
					<Device d:type="cDeltaString">Keyboard</Device>
					<ButtonState d:type="cDeltaString">ButtonDown</ButtonState>
					<Button d:type="cDeltaString">Key_SemiColon</Button>
					<ShiftButton d:type="cDeltaString">Shift_Control</ShiftButton>
					<Axis d:type="cDeltaString">NoAxis</Axis>
					<Name d:type="cDeltaString">ToggleControl</Name>
					<Parameter d:type="cDeltaString">ZamekBS2</Parameter>
					<NewState d:type="sInt32">0</NewState>
				</iInputMapper-cInputMapEntry>
				<iInputMapper-cInputMapEntry d:id="14693">
					<State d:type="sInt32">0</State>
					<Device d:type="cDeltaString">Keyboard</Device>
					<ButtonState d:type="cDeltaString">ButtonDown</ButtonState>
					<Button d:type="cDeltaString">Key_Return</Button>
					<ShiftButton d:type="cDeltaString">NoShift</ShiftButton>
					<Axis d:type="cDeltaString">NoAxis</Axis>
					<Name d:type="cDeltaString">IncreaseControlStart</Name>
					<Parameter d:type="cDeltaString">Matrosov</Parameter>
					<NewState d:type="sInt32">0</NewState>
				</iInputMapper-cInputMapEntry>
				<iInputMapper-cInputMapEntry d:id="14703">
					<State d:type="sInt32">0</State>
					<Device d:type="cDeltaString">Keyboard</Device>
					<ButtonState d:type="cDeltaString">ButtonUp</ButtonState>
					<Button d:type="cDeltaString">Key_Return</Button>
					<ShiftButton d:type="cDeltaString">NoShift</ShiftButton>
					<Axis d:type="cDeltaString">NoAxis</Axis>
					<Name d:type="cDeltaString">DecreaseControlStart</Name>
					<Parameter d:type="cDeltaString">Matrosov</Parameter>
					<NewState d:type="sInt32">0</NewState>
				</iInputMapper-cInputMapEntry>
				<iInputMapper-cInputMapEntry d:id="14713">
					<State d:type="sInt32">0</State>
					<Device d:type="cDeltaString">Keyboard</Device>
					<ButtonState d:type="cDeltaString">ButtonUp</ButtonState>
					<Button d:type="cDeltaString">Key_C</Button>
					<ShiftButton d:type="cDeltaString">Shift</ShiftButton>
					<Axis d:type="cDeltaString">NoAxis</Axis>
					<Name d:type="cDeltaString">DecreaseControlStart</Name>
					<Parameter d:type="cDeltaString">ButtonPojezdVDepu</Parameter>
					<NewState d:type="sInt32">0</NewState>
				</iInputMapper-cInputMapEntry>
				<iInputMapper-cInputMapEntry d:id="14723">
					<State d:type="sInt32">0</State>
					<Device d:type="cDeltaString">Keyboard</Device>
					<ButtonState d:type="cDeltaString">ButtonDown</ButtonState>
					<Button d:type="cDeltaString">Key_C</Button>
					<ShiftButton d:type="cDeltaString">Shift</ShiftButton>
					<Axis d:type="cDeltaString">NoAxis</Axis>
					<Name d:type="cDeltaString">IncreaseControlStart</Name>
					<Parameter d:type="cDeltaString">ButtonPojezdVDepu</Parameter>
					<NewState d:type="sInt32">0</NewState>
				</iInputMapper-cInputMapEntry>
				<iInputMapper-cInputMapEntry d:id="14733">
					<State d:type="sInt32">0</State>
					<Device d:type="cDeltaString">Keyboard</Device>
					<ButtonState d:type="cDeltaString">ButtonDown</ButtonState>
					<Button d:type="cDeltaString">Key_U</Button>
					<ShiftButton d:type="cDeltaString">NoShift</ShiftButton>
					<Axis d:type="cDeltaString">NoAxis</Axis>
					<Name d:type="cDeltaString">IncreaseControlStart</Name>
					<Parameter d:type="cDeltaString">DverePrepLevy</Parameter>
					<NewState d:type="sInt32">0</NewState>
				</iInputMapper-cInputMapEntry>
				<iInputMapper-cInputMapEntry d:id="14743">
					<State d:type="sInt32">0</State>
					<Device d:type="cDeltaString">Keyboard</Device>
					<ButtonState d:type="cDeltaString">ButtonUp</ButtonState>
					<Button d:type="cDeltaString">Key_U</Button>
					<ShiftButton d:type="cDeltaString">NoShift</ShiftButton>
					<Axis d:type="cDeltaString">NoAxis</Axis>
					<Name d:type="cDeltaString">IncreaseControlStop</Name>
					<Parameter d:type="cDeltaString">DverePrepLevy</Parameter>
					<NewState d:type="sInt32">0</NewState>
				</iInputMapper-cInputMapEntry>
				<iInputMapper-cInputMapEntry d:id="14753">
					<State d:type="sInt32">0</State>
					<Device d:type="cDeltaString">Keyboard</Device>
					<ButtonState d:type="cDeltaString">ButtonDown</ButtonState>
					<Button d:type="cDeltaString">Key_U</Button>
					<ShiftButton d:type="cDeltaString">Shift</ShiftButton>
					<Axis d:type="cDeltaString">NoAxis</Axis>
					<Name d:type="cDeltaString">DecreaseControlStart</Name>
					<Parameter d:type="cDeltaString">DverePrepLevy</Parameter>
					<NewState d:type="sInt32">0</NewState>
				</iInputMapper-cInputMapEntry>
				<iInputMapper-cInputMapEntry d:id="14763">
					<State d:type="sInt32">0</State>
					<Device d:type="cDeltaString">Keyboard</Device>
					<ButtonState d:type="cDeltaString">ButtonUp</ButtonState>
					<Button d:type="cDeltaString">Key_U</Button>
					<ShiftButton d:type="cDeltaString">Shift</ShiftButton>
					<Axis d:type="cDeltaString">NoAxis</Axis>
					<Name d:type="cDeltaString">DecreaseControlStop</Name>
					<Parameter d:type="cDeltaString">DverePrepLevy</Parameter>
					<NewState d:type="sInt32">0</NewState>
				</iInputMapper-cInputMapEntry>
				<iInputMapper-cInputMapEntry d:id="14773">
					<State d:type="sInt32">0</State>
					<Device d:type="cDeltaString">Keyboard</Device>
					<ButtonState d:type="cDeltaString">ButtonDown</ButtonState>
					<Button d:type="cDeltaString">Key_I</Button>
					<ShiftButton d:type="cDeltaString">NoShift</ShiftButton>
					<Axis d:type="cDeltaString">NoAxis</Axis>
					<Name d:type="cDeltaString">IncreaseControlStart</Name>
					<Parameter d:type="cDeltaString">DverePrepPravy</Parameter>
					<NewState d:type="sInt32">0</NewState>
				</iInputMapper-cInputMapEntry>
				<iInputMapper-cInputMapEntry d:id="14783">
					<State d:type="sInt32">0</State>
					<Device d:type="cDeltaString">Keyboard</Device>
					<ButtonState d:type="cDeltaString">ButtonUp</ButtonState>
					<Button d:type="cDeltaString">Key_I</Button>
					<ShiftButton d:type="cDeltaString">NoShift</ShiftButton>
					<Axis d:type="cDeltaString">NoAxis</Axis>
					<Name d:type="cDeltaString">IncreaseControlStop</Name>
					<Parameter d:type="cDeltaString">DverePrepPravy</Parameter>
					<NewState d:type="sInt32">0</NewState>
				</iInputMapper-cInputMapEntry>
				<iInputMapper-cInputMapEntry d:id="14793">
					<State d:type="sInt32">0</State>
					<Device d:type="cDeltaString">Keyboard</Device>
					<ButtonState d:type="cDeltaString">ButtonDown</ButtonState>
					<Button d:type="cDeltaString">Key_I</Button>
					<ShiftButton d:type="cDeltaString">Shift</ShiftButton>
					<Axis d:type="cDeltaString">NoAxis</Axis>
					<Name d:type="cDeltaString">DecreaseControlStart</Name>
					<Parameter d:type="cDeltaString">DverePrepPravy</Parameter>
					<NewState d:type="sInt32">0</NewState>
				</iInputMapper-cInputMapEntry>
				<iInputMapper-cInputMapEntry d:id="14803">
					<State d:type="sInt32">0</State>
					<Device d:type="cDeltaString">Keyboard</Device>
					<ButtonState d:type="cDeltaString">ButtonUp</ButtonState>
					<Button d:type="cDeltaString">Key_I</Button>
					<ShiftButton d:type="cDeltaString">Shift</ShiftButton>
					<Axis d:type="cDeltaString">NoAxis</Axis>
					<Name d:type="cDeltaString">DecreaseControlStop</Name>
					<Parameter d:type="cDeltaString">DverePrepPravy</Parameter>
					<NewState d:type="sInt32">0</NewState>
				</iInputMapper-cInputMapEntry>
				<iInputMapper-cInputMapEntry d:id="14813">
					<State d:type="sInt32">0</State>
					<Device d:type="cDeltaString">Keyboard</Device>
					<ButtonState d:type="cDeltaString">ButtonDown</ButtonState>
					<Button d:type="cDeltaString">Key_0</Button>
					<ShiftButton d:type="cDeltaString">Shift_Control</ShiftButton>
					<Axis d:type="cDeltaString">NoAxis</Axis>
					<Name d:type="cDeltaString">IncreaseControlStart</Name>
					<Parameter d:type="cDeltaString">Napoveda</Parameter>
					<NewState d:type="sInt32">0</NewState>
				</iInputMapper-cInputMapEntry>
				<iInputMapper-cInputMapEntry d:id="14823">
					<State d:type="sInt32">0</State>
					<Device d:type="cDeltaString">Keyboard</Device>
					<ButtonState d:type="cDeltaString">ButtonUp</ButtonState>
					<Button d:type="cDeltaString">Key_0</Button>
					<ShiftButton d:type="cDeltaString">Shift_Control</ShiftButton>
					<Axis d:type="cDeltaString">NoAxis</Axis>
					<Name d:type="cDeltaString">IncreaseControlStop</Name>
					<Parameter d:type="cDeltaString">Napoveda</Parameter>
					<NewState d:type="sInt32">0</NewState>
				</iInputMapper-cInputMapEntry>
				<iInputMapper-cInputMapEntry d:id="14833">
					<State d:type="sInt32">0</State>
					<Device d:type="cDeltaString">Keyboard</Device>
					<ButtonState d:type="cDeltaString">ButtonDown</ButtonState>
					<Button d:type="cDeltaString">NumPad_Subtract</Button>
					<ShiftButton d:type="cDeltaString">Control</ShiftButton>
					<Axis d:type="cDeltaString">NoAxis</Axis>
					<Name d:type="cDeltaString">IncreaseControlStart</Name>
					<Parameter d:type="cDeltaString">MSVdolu</Parameter>
					<NewState d:type="sInt32">0</NewState>
				</iInputMapper-cInputMapEntry>
				<iInputMapper-cInputMapEntry d:id="14843">
					<State d:type="sInt32">0</State>
					<Device d:type="cDeltaString">Keyboard</Device>
					<ButtonState d:type="cDeltaString">ButtonUp</ButtonState>
					<Button d:type="cDeltaString">NumPad_Subtract</Button>
					<ShiftButton d:type="cDeltaString">Control</ShiftButton>
					<Axis d:type="cDeltaString">NoAxis</Axis>
					<Name d:type="cDeltaString">DecreaseControlStart</Name>
					<Parameter d:type="cDeltaString">MSVdolu</Parameter>
					<NewState d:type="sInt32">0</NewState>
				</iInputMapper-cInputMapEntry>
				<iInputMapper-cInputMapEntry d:id="14853">
					<State d:type="sInt32">0</State>
					<Device d:type="cDeltaString">Keyboard</Device>
					<ButtonState d:type="cDeltaString">ButtonDown</ButtonState>
					<Button d:type="cDeltaString">NumPad_Add</Button>
					<ShiftButton d:type="cDeltaString">Control</ShiftButton>
					<Axis d:type="cDeltaString">NoAxis</Axis>
					<Name d:type="cDeltaString">IncreaseControlStart</Name>
					<Parameter d:type="cDeltaString">MSVnahoru</Parameter>
					<NewState d:type="sInt32">0</NewState>
				</iInputMapper-cInputMapEntry>
				<iInputMapper-cInputMapEntry d:id="14863">
					<State d:type="sInt32">0</State>
					<Device d:type="cDeltaString">Keyboard</Device>
					<ButtonState d:type="cDeltaString">ButtonUp</ButtonState>
					<Button d:type="cDeltaString">NumPad_Add</Button>
					<ShiftButton d:type="cDeltaString">Control</ShiftButton>
					<Axis d:type="cDeltaString">NoAxis</Axis>
					<Name d:type="cDeltaString">DecreaseControlStart</Name>
					<Parameter d:type="cDeltaString">MSVnahoru</Parameter>
					<NewState d:type="sInt32">0</NewState>
				</iInputMapper-cInputMapEntry>
				<iInputMapper-cInputMapEntry d:id="14873">
					<State d:type="sInt32">0</State>
					<Device d:type="cDeltaString">Keyboard</Device>
					<ButtonState d:type="cDeltaString">ButtonDown</ButtonState>
					<Button d:type="cDeltaString">NumPad_Divide</Button>
					<ShiftButton d:type="cDeltaString">Control</ShiftButton>
					<Axis d:type="cDeltaString">NoAxis</Axis>
					<Name d:type="cDeltaString">IncreaseControlStart</Name>
					<Parameter d:type="cDeltaString">MSVleva</Parameter>
					<NewState d:type="sInt32">0</NewState>
				</iInputMapper-cInputMapEntry>
				<iInputMapper-cInputMapEntry d:id="14883">
					<State d:type="sInt32">0</State>
					<Device d:type="cDeltaString">Keyboard</Device>
					<ButtonState d:type="cDeltaString">ButtonUp</ButtonState>
					<Button d:type="cDeltaString">NumPad_Divide</Button>
					<ShiftButton d:type="cDeltaString">Control</ShiftButton>
					<Axis d:type="cDeltaString">NoAxis</Axis>
					<Name d:type="cDeltaString">DecreaseControlStart</Name>
					<Parameter d:type="cDeltaString">MSVleva</Parameter>
					<NewState d:type="sInt32">0</NewState>
				</iInputMapper-cInputMapEntry>
				<iInputMapper-cInputMapEntry d:id="14893">
					<State d:type="sInt32">0</State>
					<Device d:type="cDeltaString">Keyboard</Device>
					<ButtonState d:type="cDeltaString">ButtonDown</ButtonState>
					<Button d:type="cDeltaString">NumPad_Multiply</Button>
					<ShiftButton d:type="cDeltaString">Control</ShiftButton>
					<Axis d:type="cDeltaString">NoAxis</Axis>
					<Name d:type="cDeltaString">IncreaseControlStart</Name>
					<Parameter d:type="cDeltaString">MSVprava</Parameter>
					<NewState d:type="sInt32">0</NewState>
				</iInputMapper-cInputMapEntry>
				<iInputMapper-cInputMapEntry d:id="14903">
					<State d:type="sInt32">0</State>
					<Device d:type="cDeltaString">Keyboard</Device>
					<ButtonState d:type="cDeltaString">ButtonUp</ButtonState>
					<Button d:type="cDeltaString">NumPad_Multiply</Button>
					<ShiftButton d:type="cDeltaString">Control</ShiftButton>
					<Axis d:type="cDeltaString">NoAxis</Axis>
					<Name d:type="cDeltaString">DecreaseControlStart</Name>
					<Parameter d:type="cDeltaString">MSVprava</Parameter>
					<NewState d:type="sInt32">0</NewState>
				</iInputMapper-cInputMapEntry>
				<iInputMapper-cInputMapEntry d:id="14913">
					<State d:type="sInt32">0</State>
					<Device d:type="cDeltaString">Keyboard</Device>
					<ButtonState d:type="cDeltaString">ButtonDown</ButtonState>
					<Button d:type="cDeltaString">NumPad_Enter</Button>
					<ShiftButton d:type="cDeltaString">Control</ShiftButton>
					<Axis d:type="cDeltaString">NoAxis</Axis>
					<Name d:type="cDeltaString">IncreaseControlStart</Name>
					<Parameter d:type="cDeltaString">MSVok</Parameter>
					<NewState d:type="sInt32">0</NewState>
				</iInputMapper-cInputMapEntry>
				<iInputMapper-cInputMapEntry d:id="14923">
					<State d:type="sInt32">0</State>
					<Device d:type="cDeltaString">Keyboard</Device>
					<ButtonState d:type="cDeltaString">ButtonUp</ButtonState>
					<Button d:type="cDeltaString">NumPad_Enter</Button>
					<ShiftButton d:type="cDeltaString">Control</ShiftButton>
					<Axis d:type="cDeltaString">NoAxis</Axis>
					<Name d:type="cDeltaString">DecreaseControlStart</Name>
					<Parameter d:type="cDeltaString">MSVok</Parameter>
					<NewState d:type="sInt32">0</NewState>
				</iInputMapper-cInputMapEntry>
			</Map>
			<MapItem />
		</cInputMapperBlueprint>
	</Blueprint>
</cBlueprintLoader>
